{
    "Anthracnose": {
        "type": "fungal",
        "fertilizer": "Balanced NPK (80:40:40 kg/acre) with micronutrients",
        "water": "65%",
        "medicine": ["Mancozeb 2.5g/liter water", "Copper oxychloride 3g/liter", "Propiconazole 1ml/liter"],
        "organic_medicine": ["Neem oil 5ml/liter water", "Trichoderma 5g/liter spray", "Sulfur dust 25kg/acre"],
        "prevention": "Remove infected leaves immediately, ensure good airflow, practice crop rotation",
        "பெயர்": "அந்திராக்னோஸ்",
        "வகை": "பூஞ்சை",
        "உரம்": "நுண்ணூட்டச்சத்துகளுடன் கூடிய சமநிலை NPK (80:40:40 kg/ஏக்கர்)",
        "நீர்": "65%",
        "மருந்து": ["மேன்கோசெப் 2.5g/லிட்டர் நீர்", "காப்பர் ஆக்சிக்ளோரைடு 3g/லிட்டர்", "புரோப்பிகோனசோல் 1ml/லிட்டர்"],
        "கரிம மருந்து": ["வேப்ப எண்ணெய் 5ml/லிட்டர் நீர்", "ட்ரைகோடெர்மா 5g/லிட்டர் தெளிப்பு", "சல்பர் தூள் 25kg/ஏக்கர்"],
        "தடுப்பு முறைகள்": "பாதிக்கப்பட்ட இலைகளை உடனடியாக அகற்றுதல், நல்ல காற்று ஓட்டம் உறுதி செய்தல், பயிர் சுழற்சி மேற்கொள்ளுதல்",
        "नाम": "ऐंथ्रेक्नोज़",
        "प्रकार": "फफूंदी",
        "उर्वरक": "सूक्ष्म पोषक तत्वों के साथ संतुलित NPK (80:40:40 kg/एकड़)",
        "पानी": "65%",
        "दवा": ["मैन्कोज़ेब 2.5g/लीटर पानी", "कॉपर ऑक्सीक्लोराइड 3g/लीटर", "प्रोपिकोनाजोल 1ml/लीटर"],
        "जैविक दवा": ["नीम का तेल 5ml/लीटर पानी", "ट्राइकोडर्मा 5g/लीटर स्प्रे", "सल्फर धूल 25kg/एकड़"],
        "रोकथाम": "संक्रमित पत्तियों को तुरंत हटाएं, अच्छी वायु प्रवाह सुनिश्चित करें, फसल चक्रण अपनाएं",
        "പേര്": "ആൻത്രാക്നോസ്",
        "തരം": "ഫംഗസ്",
        "വളം": "സൂക്ഷ്മ പോഷകങ്ങളുള്ള സന്തുലിത NPK (80:40:40 kg/ഏക്കർ)",
        "വെള്ളം": "65%",
        "മരുന്ന്": ["മാങ്കോസെബ് 2.5g/ലിറ്റർ വെള്ളം", "കോപ്പർ ഓക്സിക്ലോറൈഡ് 3g/ലിറ്റർ", "പ്രോപ്പിക്കോണസോൾ 1ml/ലിറ്റർ"],
        "ജൈവ മരുന്ന്": ["വേപ്പെണ്ണ 5ml/ലിറ്റർ വെള്ളം", "ട്രൈക്കോഡെർമ 5g/ലിറ്റർ സ്പ്രേ", "സൾഫർ പൊടി 25kg/ഏക്കർ"],
        "തടയൽ": "ബാധിച്ച ഇലകൾ ഉടൻ നീക്കം ചെയ്യുക, നല്ല വായു പ്രവാഹം ഉറപ്പാക്കുക, കൃഷി ചക്രം പാലിക്കുക",
        "పేరు": "ఆంథ్రాక్నోస్",
        "రకం": "ఫంగస్",
        "ఎరువు": "సూక్ష్మ పోషకాలతో సమతుల్య NPK (80:40:40 kg/ఎకరం)",
        "నీరు": "65%",
        "మందు": ["మ్యాంకోజెబ్ 2.5g/లీటరు నీరు", "కాపర్ ఆక్సిక్లోరైడ్ 3g/లీటరు", "ప్రొపికోనజోల్ 1ml/లీటరు"],
        "సేంద్రియ మందు": ["వేప నూనె 5ml/లీటరు నీరు", "ట్రైకోడెర్మా 5g/లీటరు స్ప్రే", "సల్ఫర్ దుమ్ము 25kg/ఎకరం"],
        "నివారణ": "బాధిత ఆకులను వెంటనే తీసివేయండి, మంచి గాలి ప్రసరణ నిర్ధారించండి, పంట మార్పిడి ఆచరించండి",
        "ಹೆಸರು": "ಆಂಥ್ರಾಕ್ನೋಸ್",
        "ರೀತಿ": "ಶಿಲೀಂಧ್ರ",
        "ಎರುವು": "ಸೂಕ್ಷ್ಮ ಪೋಷಕಾಂಶಗಳೊಂದಿಗೆ ಸಮತೋಲಿತ NPK (80:40:40 kg/ಎಕರೆ)",
        "ನೀರು": "65%",
        "ಮದ್ದು": ["ಮ್ಯಾಂಕೋಜೆಬ್ 2.5g/ಲೀಟರ್ ನೀರು", "ಕಾಪರ್ ಆಕ್ಸಿಕ್ಲೋರೈಡ್ 3g/ಲೀಟರ್", "ಪ್ರೊಪಿಕೊನಜೋಲ್ 1ml/ಲೀಟರ್"],
        "ಸಾವಯವ ಮದ್ದು": ["ಬೇವಿನ ಎಣ್ಣೆ 5ml/ಲೀಟರ್ ನೀರು", "ಟ್ರೈಕೋಡರ್ಮ 5g/ಲೀಟರ್ ಸಿಂಪಡಿಕೆ", "ಸಲ್ಫರ್ ಪುಡಿ 25kg/ಎಕರೆ"],
        "ತಡೆಗಟ್ಟುವಿಕೆ": "ಬಾಧಿತ ಎಲೆಗಳನ್ನು ತಕ್ಷಣ ತೆಗೆದುಹಾಕಿ, ಉತ್ತಮ ವಾಯು ಹರಿವು ಖಚಿತಪಡಿಸಿ, ಬೆಳೆ ಚಕ್ರಣ ಪಾಲಿಸಿ",
        "نام": "این تھریک نو س",
        "قسم": "فنگس",
        "کھاد": "مائیکرو نیوٹرینٹس کے ساتھ متوازن NPK (80:40:40 kg/ایکڑ)",
        "پانی": "65%",
        "دوا": ["مینکوزیب 2.5g/لٹر پانی", "کاپر آکسی کلورائیڈ 3g/لٹر", "پروپیکونازول 1ml/لٹر"],
        "نامیاتی دوا": ["نیم کا تیل 5ml/لٹر پانی", "ٹرائیکوڈرما 5g/لٹر سپرے", "سلفر دھول 25kg/ایکڑ"],
        "روک تھام": "متاثرہ پتیوں کو فوری ہٹائیں، اچھی ہوا کا بہاؤ یقینی بنائیں، فصل کی گردش اپنائیں"
    },

    "bark eating catterpillar":{
        "type": "insect pest",
        "fertilizer": "Balanced NPK (80:40:40 kg/acre) with micronutrients",
        "water": "60%",
        "medicine": ["Monocrotophos 1.5ml/liter water", "Carbaryl 2g/liter water", "Dichlorvos 1ml/liter water"],
        "organic_medicine": ["Neem oil 10ml/liter water", "Karanj oil 5ml/liter water", "Garlic extract 15ml/liter water"],
        "prevention": "Remove loose bark, maintain tree health, use sticky bands on trunks",
        "பெயர்": "பட்டை தின்ற கம்பளிப்பூச்சி",
        "வகை": "பூச்சி கொல்லி",
        "உரம்": "நுண்ணூட்டச்சத்துகளுடன் கூடிய சமநிலை NPK (80:40:40 kg/ஏக்கர்)",
        "நீர்": "60%",
        "மருந்து": ["மோனோகிரோடோபோஸ் 1.5ml/லிட்டர் நீர்", "கார்பேரில் 2g/லிட்டர் நீர்", "டைக்ளோர்வாஸ் 1ml/லிட்டர் நீர்"],
        "கரிம மருந்து": ["வேப்ப எண்ணெய் 10ml/லிட்டர் நீர்", "கரஞ்ச எண்ணெய் 5ml/லிட்டர் நீர்", "பூண்டு சாறு 15ml/லிட்டர் நீர்"],
        "தடுப்பு முறைகள்": "தளர்வான பட்டைகளை அகற்றுதல், மரத்தின் ஆரோக்கியத்தை பேணுதல், தண்டுகளில் ஒட்டும் பட்டைகளைப் பயன்படுத்துதல்",
        "नाम": "छाल खाने वाला इल्ली",
        "प्रकार": "कीट कीट",
        "उर्वरक": "सूक्ष्म पोषक तत्वों के साथ संतुलित NPK (80:40:40 kg/एकड़)",
        "पानी": "60%",
        "दवा": ["मोनोक्रोटोफोस 1.5ml/लीटर पानी", "कार्बेरिल 2g/लीटर पानी", "डाइक्लोरवोस 1ml/लीटर पानी"],
        "जैविक दवा": ["नीम का तेल 10ml/लीटर पानी", "करंज का तेल 5ml/लीटर पानी", "लहसुन का अर्क 15ml/लीटर पानी"],
        "रोकथाम": "ढीली छाल हटाएं, पेड़ के स्वास्थ्य को बनाए रखें, तनों पर चिपचिपे बैंड का उपयोग करें",
        "പേര്": "തൊലി തിന്നുന്ന കാട്ടുതുള്ളൻ",
        "തരം": "പ്രാണികൾ",
        "വളം": "സൂക്ഷ്മ പോഷകങ്ങളുള്ള സന്തുലിത NPK (80:40:40 kg/ഏക്കർ)",
        "വെള്ളം": "60%",
        "മരുന്ന്": ["മോണോക്രോട്ടോഫോസ് 1.5ml/ലിറ്റർ വെള്ളം", "കാർബരിൽ 2g/ലിറ്റർ വെള്ളം", "ഡൈക്ലോർവോസ് 1ml/ലിറ്റർ വെള്ളം"],
        "ജൈവ മരുന്ന്": ["വേപ്പെണ്ണ 10ml/ലിറ്റർ വെള്ളം", "കരിഞ്ചണ്ണ 5ml/ലിറ്റർ വെള്ളം", "വെളുത്തുള്ളി സത്ത് 15ml/ലിറ്റർ വെള്ളം"],
        "തടയൽ": "അയഞ്ഞ തൊലി നീക്കംചെയ്യുക, വൃക്ഷത്തിന്റെ ആരോഗ്യം നിലനിർത്തുക, തണ്ടുകളിൽ ഒട്ടുന്ന ബാൻഡുകൾ ഉപയോഗിക്കുക",
        "పేరు": "బెరడు తినే గొంగళి పురుగు",
        "రకం": "కీటకం",
        "ఎరువు": "సూక్ష్మ పోషకాలతో సమతుల్య NPK (80:40:40 kg/ఎకరం)",
        "నీరు": "60%",
        "మందు": ["మోనోక్రోటోఫాస్ 1.5ml/లీటరు నీరు", "కార్బరిల్ 2g/లీటరు నీరు", "డైక్లోర్వోస్ 1ml/లీటరు నీరు"],
        "సేంద్రియ మందు": ["వేప నూనె 10ml/లీటరు నీరు", "కరంజ నూనె 5ml/లీటరు నీరు", "వెల్లుల్లి సారం 15ml/లీటరు నీరు"],
        "నివారణ": "వదులుగా ఉన్న బెరడును తీసివేయండి, చెట్టు ఆరోగ్యాన్ని నిర్వహించండి, కాండాలపై జిగట బ్యాండ్లను ఉపయోగించండి",
        "ಹೆಸರು": "ಬೊಟ್ಟು ತಿನ್ನುವ ಕಾಂಡದ ಹುಳು",
        "ರೀತಿ": "ಕೀಟ",
        "ಎರುವು": "ಸೂಕ್ಷ್ಮ ಪೋಷಕಾಂಶಗಳೊಂದಿಗೆ ಸಮತೋಲಿತ NPK (80:40:40 kg/ಎಕರೆ)",
        "ನೀರು": "60%",
        "ಮದ್ದು": ["ಮೊನೊಕ್ರೊಟೊಫೋಸ್ 1.5ml/ಲೀಟರ್ ನೀರು", "ಕಾರ್ಬರಿಲ್ 2g/ಲೀಟರ್ ನೀರು", "ಡೈಕ್ಲೋರ್ವೋಸ್ 1ml/ಲೀಟರ್ ನೀರು"],
        "ಸಾವಯವ ಮದ್ದು": ["ಬೇವಿನ ಎಣ್ಣೆ 10ml/ಲೀಟರ್ ನೀರು", "ಕರಂಜ ಎಣ್ಣೆ 5ml/ಲೀಟರ್ ನೀರು", "ಬೆಳ್ಳುಳ್ಳಿ ಸಾರ 15ml/ಲೀಟರ್ ನೀರು"],
        "ತಡೆಗಟ್ಟುವಿಕೆ": "ಅಗುರು ತೊಗಟೆಯನ್ನು ತೆಗೆದುಹಾಕಿ, ಮರದ ಆರೋಗ್ಯವನ್ನು ಕಾಪಾಡಿಕೊಳ್ಳಿ, ಕಾಂಡಗಳ ಮೇಲೆ ಅಂಟು ಪಟ್ಟಿಗಳನ್ನು ಬಳಸಿ",
        "نام": "چھال کھانے والا سنڈی",
        "قسم": "کیڑا",
        "کھاد": "مائیکرو نیوٹرینٹس کے ساتھ متوازن NPK (80:40:40 kg/ایکڑ)",
        "پانی": "60%",
        "دوا": ["مونوکروٹوفوس 1.5ml/لٹر پانی", "کاربیرل 2g/لٹر پانی", "ڈائیکلورووس 1ml/لٹر پانی"],
        "نامیاتی دوا": ["نیم کا تیل 10ml/لٹر پانی", "کرنج کا تیل 5ml/لٹر پانی", "لہسن کا عرق 15ml/لٹر پانی"],
        "روک تھام": "ڈھیلی چھال ہٹائیں، درخت کی صحت برقرار رکھیں، تنا پر چپکنے والے بینڈ استعمال کریں"
    },

    "Damping_Off": {
        "type": "fungal",
        "fertilizer": "Balanced NPK (80:40:40 kg/acre) with micronutrients",
        "water": "55%",
        "medicine": ["Metalaxyl 2g/liter water", "Captan 2g/liter water", "Thiram 3g/liter water"],
        "organic_medicine": ["Trichoderma 10g/liter water", "Pseudomonas fluorescens 10g/liter", "Neem cake 100kg/acre"],
        "prevention": "Use sterilized soil, avoid overwatering, ensure good drainage",
        "பெயர்": "தழைக்காம்பு அழுகல்",
        "வகை": "பூஞ்சை",
        "உரம்": "நுண்ணூட்டச்சத்துகளுடன் கூடிய சமநிலை NPK (80:40:40 kg/ஏக்கர்)",
        "நீர்": "55%",
        "மருந்து": ["மெட்டலாக்ஸில் 2g/லிட்டர் நீர்", "கேப்டன் 2g/லிட்டர் நீர்", "தைரம் 3g/லிட்டர் நீர்"],
        "கரிம மருந்து": ["ட்ரைகோடெர்மா 10g/லிட்டர் நீர்", "சூடோமோனாஸ் புளோரசன்ஸ் 10g/லிட்டர்", "வேம்பு கேக் 100kg/ஏக்கர்"],
        "தடுப்பு முறைகள்": "துப்புரவு செய்யப்பட்ட மண்ணைப் பயன்படுத்துதல், அதிக நீர்ப்பாசனம் தவிர்த்தல், நல்ல வடிகால் உறுதி செய்தல்",
        "नाम": "डैम्पिंग ऑफ",
        "प्रकार": "फफूंदी",
        "उर्वरक": "सूक्ष्म पोषक तत्वों के साथ संतुलित NPK (80:40:40 kg/एकड़)",
        "पानी": "55%",
        "दवा": ["मेटालैक्सिल 2g/लीटर पानी", "कैप्टन 2g/लीटर पानी", "थिरम 3g/लीटर पानी"],
        "जैविक दवा": ["ट्राइकोडर्मा 10g/लीटर पानी", "स्यूडोमोनास फ्लोरोसेंस 10g/लीटर", "नीम की खली 100kg/एकड़"],
        "रोकथाम": "बाँझ मिट्टी का उपयोग करें, अतिरिक्त पानी देने से बचें, अच्छी जल निकासी सुनिश्चित करें",
        "പേര്": "ഡാമ്പിംഗ് ഓഫ്",
        "തരം": "ഫംഗസ്",
        "വളം": "സൂക്ഷ്മ പോഷകങ്ങളുള്ള സന്തുലിത NPK (80:40:40 kg/ഏക്കർ)",
        "വെള്ളം": "55%",
        "മരുന്ന്": ["മെറ്റാലാക്സിൽ 2g/ലിറ്റർ വെള്ളം", "കാപ്റ്റൻ 2g/ലിറ്റർ വെള്ളം", "തൈറം 3g/ലിറ്റർ വെള്ളം"],
        "ജൈവ മരുന്ന്": ["ട്രൈക്കോഡെർമ 10g/ലിറ്റർ വെള്ളം", "സ്യൂഡോമോണാസ് ഫ്ലൂറസെൻസ് 10g/ലിറ്റർ", "വേപ്പുമാവ് 100kg/ഏക്കർ"],
        "തടയൽ": "ശുദ്ധീകരിച്ച മണ്ണ് ഉപയോഗിക്കുക, അമിത നീരൊഴുക്ക് ഒഴിവാക്കുക, നല്ല ജലനിരപ്പ് ഉറപ്പാക്കുക",
        "పేరు": "డంపింగ్ ఆఫ్",
        "రకం": "ఫంగస్",
        "ఎరువు": "సూక్ష్మ పోషకాలతో సమతుల్య NPK (80:40:40 kg/ఎకరం)",
        "నీరు": "55%",
        "మందు": ["మెటాలాక్సిల్ 2g/లీటరు నీరు", "క్యాప్టన్ 2g/లీటరు నీరు", "తైరం 3g/లీటరు నీరు"],
        "సేంద్రియ మందు": ["ట్రైకోడెర్మా 10g/లీటరు నీరు", "సూడోమోనాస్ ఫ్లోరసెన్స్ 10g/లీటరు", "వేప చెక్క 100kg/ఎకరం"],
        "నివారణ": "శుభ్రపరచిన నేలను ఉపయోగించండి, అధిక నీటిపారుదల నివారించండి, మంచి నీటి వద్దులను నిర్ధారించండి",
        "ಹೆಸರು": "ಡ್ಯಾಂಪಿಂಗ್ ಆಫ್",
        "ರೀತಿ": "ಶಿಲೀಂಧ್ರ",
        "ಎರುವು": "ಸೂಕ್ಷ್ಮ ಪೋಷಕಾಂಶಗಳೊಂದಿಗೆ ಸಮತೋಲಿತ NPK (80:40:40 kg/ಎಕರೆ)",
        "ನೀರು": "55%",
        "ಮದ್ದು": ["ಮೆಟಾಲಾಕ್ಸಿಲ್ 2g/ಲೀಟರ್ ನೀರು", "ಕ್ಯಾಪ್ಟನ್ 2g/ಲೀಟರ್ ನೀರು", "ಥೈರಮ್ 3g/ಲೀಟರ್ ನೀರು"],
        "ಸಾವಯವ ಮದ್ದು": ["ಟ್ರೈಕೋಡರ್ಮ 10g/ಲೀಟರ್ ನೀರು", "ಸೂಡೋಮೊನಾಸ್ ಫ್ಲೂರಸೆನ್ಸ್ 10g/ಲೀಟರ್", "ಬೇವಿನ ಹಿಂಡಿ 100kg/ಎಕರೆ"],
        "ತಡೆಗಟ್ಟುವಿಕೆ": "ಶುಚಿಗೊಳಿಸಿದ ಮಣ್ಣನ್ನು ಬಳಸಿ, ಅತಿಯಾದ ನೀರಾವರಿ ತಪ್ಪಿಸಿ, ಉತ್ತಮ ಜಲನಿಕ್ಷೇಪ ಖಾತರಿಪಡಿಸಿ",
        "نام": "ڈیمپنگ آف",
        "قسم": "فنگس",
        "کھاد": "مائیکرو نیوٹرینٹس کے ساتھ متوازن NPK (80:40:40 kg/ایکڑ)",
        "پانی": "55%",
        "دوا": ["میٹالاکسل 2g/لٹر پانی", "کیپٹن 2g/لٹر پانی", "تھیرم 3g/لٹر پانی"],
        "نامیاتی دوا": ["ٹرائیکوڈرما 10g/لٹر پانی", "سوڈوموناس فلورسینس 10g/لٹر", "نیم کا کیک 100kg/ایکڑ"],
        "روک تھام": "جراثیم سے پاک مٹی استعمال کریں، زیادہ پانی دینے سے گریز کریں، اچھی نکاسی آب یقینی بنائیں"
    },

    "Fusarium_Wilt": {
        "type": "fungal",
        "fertilizer": "Balanced NPK (80:40:40 kg/acre) with micronutrients",
        "water": "60%",
        "medicine": ["Carbendazim 1g/liter water", "Benomyl 1g/liter water", "Thiophanate-methyl 1.5g/liter"],
        "organic_medicine": ["Trichoderma viride 10g/liter water", "Neem oil 5ml/liter water", "Garlic extract 10ml/liter"],
        "prevention": "Use resistant varieties, practice crop rotation, avoid waterlogging",
        "பெயர்": "ஃபியூசேரியம் வாடல்",
        "வகை": "பூஞ்சை",
        "உரம்": "நுண்ணூட்டச்சத்துகளுடன் கூடிய சமநிலை NPK (80:40:40 kg/ஏக்கர்)",
        "நீர்": "60%",
        "மருந்து": ["கார்பெண்டாசிம் 1g/லிட்டர் நீர்", "பெனோமில் 1g/லிட்டர் நீர்", "தையோபெனேட்-மெத்தில் 1.5g/லிட்டர்"],
        "கரிம மருந்து": ["ட்ரைகோடெர்மா வைரிடே 10g/லிட்டர் நீர்", "வேப்ப எண்ணெய் 5ml/லிட்டர் நீர்", "பூண்டு சாறு 10ml/லிட்டர் நீர்"],
        "தடுப்பு முறைகள்": "எதிர்ப்புத் திறன் கொண்ட வகைகளைப் பயன்படுத்துதல், பயிர் சுழற்சி மேற்கொள்ளுதல், நீர் தேங்குதலைத் தவிர்த்தல்",
        "नाम": "फ्यूजेरियम विल्ट",
        "प्रकार": "फफूंदी",
        "उर्वरक": "सूक्ष्म पोषक तत्वों के साथ संतुलित NPK (80:40:40 kg/एकड़)",
        "पानी": "60%",
        "दवा": ["कार्बेन्डाजिम 1g/लीटर पानी", "बेनोमिल 1g/लीटर पानी", "थायोफेनेट-मेथिल 1.5g/लीटर"],
        "जैविक दवा": ["ट्राइकोडर्मा वाइराइड 10g/लीटर पानी", "नीम का तेल 5ml/लीटर पानी", "लहसुन का अर्क 10ml/लीटर पानी"],
        "रोकथाम": "प्रतिरोधी किस्मों का उपयोग करें, फसल चक्रण अपनाएं, जलभराव से बचें",
        "പേര്": "ഫ്യൂസേറിയം വിൽട്ട്",
        "തരം": "ഫംഗസ്",
        "വളം": "സൂക്ഷ്മ പോഷകങ്ങളുള്ള സന്തുലിത NPK (80:40:40 kg/ഏക്കർ)",
        "വെള്ളം": "60%",
        "മരുന്ന്": ["കാർബൻഡാസിം 1g/ലിറ്റർ വെള്ളം", "ബെനോമിൽ 1g/ലിറ്റർ വെള്ളം", "തിയോഫനേറ്റ്-മെത്തിൽ 1.5g/ലിറ്റർ"],
        "ജൈവ മരുന്ന്": ["ട്രൈക്കോഡെർമ വിരിഡെ 10g/ലിറ്റർ വെള്ളം", "വേപ്പെണ്ണ 5ml/ലിറ്റർ വെള്ളം", "വെളുത്തുള്ളി സത്ത് 10ml/ലിറ്റർ വെള്ളം"],
        "തടയൽ": "പ്രതിരോധ ഇനങ്ങൾ ഉപയോഗിക്കുക, കൃഷി ചക്രം പാലിക്കുക, വെള്ളം തങ്ങൽ ഒഴിവാക്കുക",
        "పేరు": "ఫ్యూజేరియం విల్ట్",
        "రకం": "ఫంగస్",
        "ఎరువు": "సూక్ష్మ పోషకాలతో సమతుల్య NPK (80:40:40 kg/ఎకరం)",
        "నీరు": "60%",
        "మందు": ["కార్బెండాజిమ్ 1g/లీటరు నీరు", "బెనోమిల్ 1g/లీటరు నీరు", "థియోఫెనేట్-మిథైల్ 1.5g/లీటరు"],
        "సేంద్రియ మందు": ["ట్రైకోడెర్మా వైరిడే 10g/లీటరు నీరు", "వేప నూనె 5ml/లీటరు నీరు", "వెల్లుల్లి సారం 10ml/లీటరు నీరు"],
        "నివారణ": "నిరోధక రకాలను ఉపయోగించండి, పంట మార్పిడి ఆచరించండి, నీటి నిల్వలను నివారించండి",
        "ಹೆಸರು": "ಫ್ಯೂಸೇರಿಯಂ ವಿಲ್ಟ್",
        "ರೀತಿ": "ಶಿಲೀಂಧ್ರ",
        "ಎರುವು": "ಸೂಕ್ಷ್ಮ ಪೋಷಕಾಂಶಗಳೊಂದಿಗೆ ಸಮತೋಲಿತ NPK (80:40:40 kg/ಎಕರೆ)",
        "ನೀರು": "60%",
        "ಮದ್ದು": ["ಕಾರ್ಬೆಂಡಾಜಿಮ್ 1g/ಲೀಟರ್ ನೀರು", "ಬೆನೋಮಿಲ್ 1g/ಲೀಟರ್ ನೀರು", "ಥಯೋಫೆನೇಟ್-ಮೆಥೈಲ್ 1.5g/ಲೀಟರ್"],
        "ಸಾವಯವ ಮದ್ದು": ["ಟ್ರೈಕೋಡರ್ಮ ವಿರಿಡೆ 10g/ಲೀಟರ್ ನೀರು", "ಬೇವಿನ ಎಣ್ಣೆ 5ml/ಲೀಟರ್ ನೀರು", "ಬೆಳ್ಳುಳ್ಳಿ ಸಾರ 10ml/ಲೀಟರ್ ನೀರು"],
        "ತಡೆಗಟ್ಟುವಿಕೆ": "ನಿರೋಧಕ ತಳಿಗಳನ್ನು ಬಳಸಿ, ಬೆಳೆ ಚಕ್ರಣ ಪಾಲಿಸಿ, ನೀರು ತುಂಬಿಕೊಳ್ಳುವುದನ್ನು ತಪ್ಪಿಸಿ",
        "نام": "فیوزیریم ولٹ",
        "قسم": "فنگس",
        "کھاد": "مائیکرو نیوٹرینٹس کے ساتھ متوازن NPK (80:40:40 kg/ایکڑ)",
        "پانی": "60%",
        "دوا": ["کاربینڈازیم 1g/لٹر پانی", "بینومیل 1g/لٹر پانی", "تھائیوفینیٹ میتھائل 1.5g/لٹر"],
        "نامیاتی دوا": ["ٹرائیکوڈرما ویرائڈی 10g/لٹر پانی", "نیم کا تیل 5ml/لٹر پانی", "لہسن کا عرق 10ml/لٹر پانی"],
        "روک تھام": "مزاحم اقسام استعمال کریں، فصل کی گردش اپنائیں، پانی بھرنے سے بچیں"
    },

    "Healthy": {
        "type": "healthy",
        "fertilizer": "Balanced NPK (80:40:40 kg/acre) with micronutrients",
        "water": "70%",
        "medicine": ["No chemical medicine required"],
        "organic_medicine": ["Regular neem oil spray 5ml/liter every 15 days", "Trichoderma application 5g/liter monthly"],
        "prevention": "Maintain proper irrigation, regular monitoring, balanced fertilization",
        "பெயர்": "ஆரோக்கியமான",
        "வகை": "ஆரோக்கியமான",
        "உரம்": "நுண்ணூட்டச்சத்துகளுடன் கூடிய சமநிலை NPK (80:40:40 kg/ஏக்கர்)",
        "நீர்": "70%",
        "மருந்து": ["ரசாயன மருந்து தேவையில்லை"],
        "கரிம மருந்து": ["வேப்ப எண்ணெய் தெளிப்பு 5ml/லிட்டர் 15 நாட்களுக்கு ஒருமுறை", "ட்ரைகோடெர்மா பயன்பாடு 5g/லிட்டர் மாதத்திற்கு ஒருமுறை"],
        "தடுப்பு முறைகள்": "சரியான நீர்ப்பாசனம் பராமரித்தல், வழக்கமான கண்காணிப்பு, சமநிலை உரமிடுதல்",
        "नाम": "स्वस्थ",
        "प्रकार": "स्वस्थ",
        "उर्वरक": "सूक्ष्म पोषक तत्वों के साथ संतुलित NPK (80:40:40 kg/एकड़)",
        "पानी": "70%",
        "दवा": ["रासायनिक दवा की आवश्यकता नहीं"],
        "जैविक दवा": ["नियमित नीम का तेल स्प्रे 5ml/लीटर हर 15 दिन", "ट्राइकोडर्मा अनुप्रयोग 5g/लीटर मासिक"],
        "रोकथाम": "उचित सिंचाई बनाए रखें, नियमित निगरानी, संतुलित उर्वरक",
        "പേര്": "ആരോഗ്യമുള്ള",
        "തരം": "ആരോഗ്യമുള്ള",
        "വളം": "സൂക്ഷ്മ പോഷകങ്ങളുള്ള സന്തുലിത NPK (80:40:40 kg/ഏക്കർ)",
        "വെള്ളം": "70%",
        "മരുന്ന്": ["രാസ മരുന്ന് ആവശ്യമില്ല"],
        "ജൈവ മരുന്ന്": ["വേപ്പെണ്ണ സ്പ്രേ 5ml/ലിറ്റർ ഓരോ 15 ദിവസം കൂടി", "ട്രൈക്കോഡെർമ പ്രയോഗം 5g/ലിറ്റർ പ്രതിമാസം"],
        "തടയൽ": "ഉചിതമായ ജലസേചനം നിലനിർത്തുക, സാധാരണ നിരീക്ഷണം, സമതുലിത വളപ്രയോഗം",
        "పేరు": "ఆరోగ్యకరమైన",
        "రకం": "ఆరోగ్యకరమైన",
        "ఎరువు": "సూక్ష్మ పోషకాలతో సమతుల్య NPK (80:40:40 kg/ఎకరం)",
        "నీరు": "70%",
        "మందు": ["రసాయన మందు అవసరం లేదు"],
        "సేంద్రియ మందు": ["వేప నూనె స్ప్రే 5ml/లీటరు ప్రతి 15 రోజులకు", "ట్రైకోడెర్మా అప్లికేషన్ 5g/లీటరు నెలవారీగా"],
        "నివారణ": "సరియైన నీటిపారుదల నిర్వహించండి, సాధారణ పర్యవేక్షణ, సమతుల్య ఎరువు వేసే పద్ధతి",
        "ಹೆಸರು": "ಆರೋಗ್ಯಕರ",
        "ರೀತಿ": "ಆರೋಗ್ಯಕರ",
        "ಎರುವು": "ಸೂಕ್ಷ್ಮ ಪೋಷಕಾಂಶಗಳೊಂದಿಗೆ ಸಮತೋಲಿತ NPK (80:40:40 kg/ಎಕರೆ)",
        "ನೀರು": "70%",
        "ಮದ್ದು": ["ರಾಸಾಯನಿಕ ಮದ್ದು ಅಗತ್ಯವಿಲ್ಲ"],
        "ಸಾವಯವ ಮದ್ದು": ["ನಿಯಮಿತ ಬೇವಿನ ಎಣ್ಣೆ ಸಿಂಪಡಣೆ 5ml/ಲೀಟರ್ ಪ್ರತಿ 15 ದಿನಗಳಿಗೊಮ್ಮೆ", "ಟ್ರೈಕೋಡರ್ಮ ಅನ್ವಯ 5g/ಲೀಟರ್ ಮಾಸಿಕ"],
        "ತಡೆಗಟ್ಟುವಿಕೆ": "ಸರಿಯಾದ ನೀರಾವರಿ ನಿರ್ವಹಿಸಿ, ನಿಯಮಿತ ಮೇಲ್ವಿಚಾರಣೆ, ಸಮತೋಲನ ರೀತಿಯ ಗೊಬ್ಬರ ಲಗತ್ತಿಸುವಿಕೆ",
        "نام": "صحت مند",
        "قسم": "صحت مند",
        "کھاد": "مائیکرو نیوٹرینٹس کے ساتھ متوازن NPK (80:40:40 kg/ایکڑ)",
        "پانی": "70%",
        "دوا": ["کیمیائی دوا کی ضرورت نہیں"],
        "نامیاتی دوا": ["باقاعدہ نیم کا تیل سپرے 5ml/لٹر ہر 15 دن بعد", "ٹرائیکوڈرما اطلاق 5g/لٹر ماہانہ"],
        "روک تھام": "مناسب آبپاشی برقرار رکھیں، باقاعدہ نگرانی، متوازن کھاد"
    },

    "leaf blight": {
        "type": "fungal",
        "fertilizer": "Balanced NPK (80:40:40 kg/acre) with micronutrients",
        "water": "65%",
        "medicine": ["Chlorothalonil 2g/liter water", "Mancozeb 2.5g/liter water", "Copper hydroxide 3g/liter"],
        "organic_medicine": ["Neem oil 5ml/liter water", "Baking soda solution 5g/liter", "Garlic extract 10ml/liter"],
        "prevention": "Remove infected leaves, avoid overhead irrigation, ensure proper spacing",
        "பெயர்": "இலை கருகல்",
        "வகை": "பூஞ்சை",
        "உரம்": "நுண்ணூட்டச்சத்துகளுடன் கூடிய சமநிலை NPK (80:40:40 kg/ஏக்கர்)",
        "நீர்": "65%",
        "மருந்து": ["குளோரோதலோனில் 2g/லிட்டர் நீர்", "மேன்கோசெப் 2.5g/லிட்டர் நீர்", "காப்பர் ஹைட்ராக்சைடு 3g/லிட்டர்"],
        "கரிம மருந்து": ["வேப்ப எண்ணெய் 5ml/லிட்டர் நீர்", "பேக்கிங் சோடா கரைசல் 5g/லிட்டர்", "பூண்டு சாறு 10ml/லிட்டர் நீர்"],
        "தடுப்பு முறைகள்": "பாதிக்கப்பட்ட இலைகளை அகற்றுதல், மேல் நீர்ப்பாசனம் தவிர்த்தல், சரியான இடைவெளி உறுதி செய்தல்",
        "नाम": "पत्ती झुलसा",
        "प्रकार": "फफूंदी",
        "उर्वरक": "सूक्ष्म पोषक तत्वों के साथ संतुलित NPK (80:40:40 kg/एकड़)",
        "पानी": "65%",
        "दवा": ["क्लोरोथैलोनिल 2g/लीटर पानी", "मैन्कोज़ेब 2.5g/लीटर पानी", "कॉपर हाइड्रॉक्साइड 3g/लीटर"],
        "जैविक दवा": ["नीम का तेल 5ml/लीटर पानी", "बेकिंग सोडा घोल 5g/लीटर", "लहसुन का अर्क 10ml/लीटर पानी"],
        "रोकथाम": "संक्रमित पत्तियों को हटाएं, ऊपरी सिंचाई से बचें, उचित अंतर सुनिश्चित करें",
        "പേര്": "ഇല കരിപ്പ്",
        "തരം": "ഫംഗസ്",
        "വളം": "സൂക്ഷ്മ പോഷകങ്ങളുള്ള സന്തുലിത NPK (80:40:40 kg/ഏക്കർ)",
        "വെള്ളം": "65%",
        "മരുന്ന്": ["ക്ലോറോതലോനിൽ 2g/ലിറ്റർ വെള്ളം", "മാങ്കോസെബ് 2.5g/ലിറ്റർ വെള്ളം", "കോപ്പർ ഹൈഡ്രോക്സൈഡ് 3g/ലിറ്റർ"],
        "ജൈവ മരുന്ന്": ["വേപ്പെണ്ണ 5ml/ലിറ്റർ വെള്ളം", "ബേക്കിംഗ് സോഡ ലായനി 5g/ലിറ്റർ", "വെളുത്തുള്ളി സത്ത് 10ml/ലിറ്റർ വെള്ളം"],
        "തടയൽ": "ബാധിച്ച ഇലകൾ നീക്കം ചെയ്യുക, മുകളിലൂടെയുള്ള ജലസേചനം ഒഴിവാക്കുക, ശരിയായ അകലം ഉറപ്പാക്കുക",
        "పేరు": "ఆకు బ్లైట్",
        "రకం": "ఫంగస్",
        "ఎరువు": "సూక్ష్మ పోషకాలతో సమతుల్య NPK (80:40:40 kg/ఎకరం)",
        "నీరు": "65%",
        "మందు": ["క్లోరోతలోనిల్ 2g/లీటరు నీరు", "మ్యాంకోజెబ్ 2.5g/లీటరు నీరు", "కాపర్ హైడ్రాక్సైడ్ 3g/లీటరు"],
        "సేంద్రియ మందు": ["వేప నూనె 5ml/లీటరు నీరు", "బేకింగ్ సోడా ద్రావణం 5g/లీటరు", "వెల్లుల్లి సారం 10ml/లీటరు నీరు"],
        "నివారణ": "బాధిత ఆకులను తీసివేయండి, పై నీటిపారుదల నివారించండి, సరైన అంతరాన్ని నిర్ధారించండి",
        "ಹೆಸರು": "ಎಲೆ ಬ್ಲೈಟ್",
        "ರೀತಿ": "ಶಿಲೀಂಧ್ರ",
        "ಎರುವು": "ಸೂಕ್ಷ್ಮ ಪೋಷಕಾಂಶಗಳೊಂದಿಗೆ ಸಮತೋಲಿತ NPK (80:40:40 kg/ಎಕರೆ)",
        "ನೀರು": "65%",
        "ಮದ್ದು": ["ಕ್ಲೋರೋತಲೋನಿಲ್ 2g/ಲೀಟರ್ ನೀರು", "ಮ್ಯಾಂಕೋಜೆಬ್ 2.5g/ಲೀಟರ್ ನೀರು", "ಕಾಪರ್ ಹೈಡ್ರಾಕ್ಸೈಡ್ 3g/ಲೀಟರ್"],
        "ಸಾವಯವ ಮದ್ದು": ["ಬೇವಿನ ಎಣ್ಣೆ 5ml/ಲೀಟರ್ ನೀರು", "ಬೇಕಿಂಗ್ ಸೋಡಾ ದ್ರಾವಣ 5g/ಲೀಟರ್", "ಬೆಳ್ಳುಳ್ಳಿ ಸಾರ 10ml/ಲೀಟರ್ ನೀರು"],
        "ತಡೆಗಟ್ಟುವಿಕೆ": "ಬಾಧಿತ ಎಲೆಗಳನ್ನು ತೆಗೆದುಹಾಕಿ, ಮೇಲಿನ ನೀರಾವರಿ ತಪ್ಪಿಸಿ, ಸರಿಯಾದ ಅಂತರ ಖಾತರಿಪಡಿಸಿ",
        "نام": "پتی کا بلائٹ",
        "قسم": "فنگس",
        "کھاد": "مائیکرو نیوٹرینٹس کے ساتھ متوازن NPK (80:40:40 kg/ایکڑ)",
        "پانی": "65%",
        "دوا": ["کلوروتھیلونیل 2g/لٹر پانی", "مینکوزیب 2.5g/لٹر پانی", "کاپر ہائیڈرو آکسائیڈ 3g/لٹر"],
        "نامیاتی دوا": ["نیم کا تیل 5ml/لٹر پانی", "بیکنگ سوڈا محلول 5g/لٹر", "لہسن کا عرق 10ml/لٹر پانی"],
        "روک تھام": "متاثرہ پتیوں کو ہٹائیں، اوور ہیڈ آبپاشی سے بچیں، مناسب فاصلہ یقینی بنائیں"
    },

    "Leaf_Rust": {
        "type": "fungal",
        "fertilizer": "Balanced NPK (80:40:40 kg/acre) with micronutrients",
        "water": "60%",
        "medicine": ["Triadimefon 1g/liter water", "Propiconazole 1ml/liter", "Hexaconazole 1ml/liter"],
        "organic_medicine": ["Neem oil 5ml/liter water", "Sulfur dust 25kg/acre", "Garlic-chilli extract 10ml/liter"],
        "prevention": "Remove infected leaves, avoid overcrowding, ensure good air circulation",
        "பெயர்": "இலை துரு",
        "வகை": "பூஞ்சை",
        "உரம்": "நுண்ணூட்டச்சத்துகளுடன் கூடிய சமநிலை NPK (80:40:40 kg/ஏக்கர்)",
        "நீர்": "60%",
        "மருந்து": ["டிரையடிமெஃபான் 1g/லிட்டர் நீர்", "புரோப்பிகோனசோல் 1ml/லிட்டர்", "ஹெக்ஸாகோனசோல் 1ml/லிட்டர்"],
        "கரிம மருந்து": ["வேப்ப எண்ணெய் 5ml/லிட்டர் நீர்", "சல்பர் தூள் 25kg/ஏக்கர்", "பூண்டு-மிளகாய் சாறு 10ml/லிட்டர்"],
        "தடுப்பு முறைகள்": "பாதிக்கப்பட்ட இலைகளை அகற்றுதல், நெரிசலைத் தவிர்த்தல், நல்ல காற்று சுழற்சி உறுதி செய்தல்",
        "नाम": "पत्ती की जंग",
        "प्रकार": "फफूंदी",
        "उर्वरक": "सूक्ष्म पोषक तत्वों के साथ संतुलित NPK (80:40:40 kg/एकड़)",
        "पानी": "60%",
        "दवा": ["ट्रायडीमेफ़ोन 1g/लीटर पानी", "प्रोपिकोनाजोल 1ml/लीटर", "हेक्साकोनाजोल 1ml/लीटर"],
        "जैविक दवा": ["नीम का तेल 5ml/लीटर पानी", "सल्फर धूल 25kg/एकड़", "लहसुन-मिर्च का अर्क 10ml/लीटर"],
        "रोकथाम": "संक्रमित पत्तियों को हटाएं, भीड़भाड़ से बचें, अच्छी वायु परिसंचरण सुनिश्चित करें",
        "പേര്": "ഇല തുരുമ്പ്",
        "തരം": "ഫംഗസ്",
        "വളം": "സൂക്ഷ്മ പോഷകങ്ങളുള്ള സന്തുലിത NPK (80:40:40 kg/ഏക്കർ)",
        "വെള്ളം": "60%",
        "മരുന്ന്": ["ട്രയാഡിമെഫോൺ 1g/ലിറ്റർ വെള്ളം", "പ്രോപ്പിക്കോണസോൾ 1ml/ലിറ്റർ", "ഹെക്സകോണസോൾ 1ml/ലിറ്റർ"],
        "ജൈവ മരുന്ന്": ["വേപ്പെണ്ണ 5ml/ലിറ്റർ വെള്ളം", "സൾഫർ പൊടി 25kg/ഏക്കർ", "വെളുത്തുള്ളി-മുളക് സത്ത് 10ml/ലിറ്റർ"],
        "തടയൽ": "ബാധിച്ച ഇലകൾ നീക്കം ചെയ്യുക, ജനസാന്ദ്രത ഒഴിവാക്കുക, നല്ല വായു പ്രചരണം ഉറപ്പാക്കുക",
        "పేరు": "ఆకు తుప్పు",
        "రకం": "ఫంగస్",
        "ఎరువు": "సూక్ష్మ పోషకాలతో సమతుల్య NPK (80:40:40 kg/ఎకరం)",
        "నీరు": "60%",
        "మందు": ["ట్రైయడీమెఫాన్ 1g/లీటరు నీరు", "ప్రొపికోనజోల్ 1ml/లీటరు", "హెక్సాకోనజోల్ 1ml/లీటరు"],
        "సేంద్రియ మందు": ["వేప నూనె 5ml/లీటరు నీరు", "సల్ఫర్ దుమ్ము 25kg/ఎకరం", "వెల్లుల్లి-మిర్చి సారం 10ml/లీటరు"],
        "నివారణ": "బాధిత ఆకులను తీసివేయండి, గుమిగూడిన స్థానాలు నివారించండి, మంచి గాలి ప్రసరణ నిర్ధారించండి",
        "ಹೆಸರು": "ಎಲೆ ತುಕ್ಕು",
        "ರೀತಿ": "ಶಿಲೀಂಧ್ರ",
        "ಎರುವು": "ಸೂಕ್ಷ್ಮ ಪೋಷಕಾಂಶಗಳೊಂದಿಗೆ ಸಮತೋಲಿತ NPK (80:40:40 kg/ಎಕರೆ)",
        "ನೀರು": "60%",
        "ಮದ್ದು": ["ಟ್ರೈಯಡಿಮೆಫಾನ್ 1g/ಲೀಟರ್ ನೀರು", "ಪ್ರೊಪಿಕೊನಜೋಲ್ 1ml/ಲೀಟರ್", "ಹೆಕ್ಸಾಕೊನಜೋಲ್ 1ml/ಲೀಟರ್"],
        "ಸಾವಯವ ಮದ್ದು": ["ಬೇವಿನ ಎಣ್ಣೆ 5ml/ಲೀಟರ್ ನೀರು", "ಸಲ್ಫರ್ ಪುಡಿ 25kg/ಎಕರೆ", "ಬೆಳ್ಳುಳ್ಳಿ-ಮೆಣಸಿನಕಾಯಿ ಸಾರ 10ml/ಲೀಟರ್"],
        "ತಡೆಗಟ್ಟುವಿಕೆ": "ಬಾಧಿತ ಎಲೆಗಳನ್ನು ತೆಗೆದುಹಾಕಿ, ಜನಸಂದಣಿ ತಪ್ಪಿಸಿ, ಉತ್ತಮ ವಾಯು ಸಂಚಾರ ಖಾತರಿಪಡಿಸಿ",
        "نام": "پتی کی زنگ",
        "قسم": "فنگس",
        "کھاد": "مائیکرو نیوٹرینٹس کے ساتھ متوازن NPK (80:40:40 kg/ایکڑ)",
        "پانی": "60%",
        "دوا": ["ٹرائیڈیمیفون 1g/لٹر پانی", "پروپیکونازول 1ml/لٹر", "ہیکساکونازول 1ml/لٹر"],
        "نامیاتی دوا": ["نیم کا تیل 5ml/لٹر پانی", "سلفر دھول 25kg/ایکڑ", "لہسن مرچ کا عرق 10ml/لٹر"],
        "روک تھام": "متاثرہ پتیوں کو ہٹائیں، بھیڑ سے بچیں، اچھی ہوا کی گردش یقینی بنائیں"
    },

    "Leaf_Spot": {
        "type": "fungal",
        "fertilizer": "Balanced NPK (80:40:40 kg/acre) with micronutrients",
        "water": "65%",
        "medicine": ["Mancozeb 2.5g/liter water", "Copper oxychloride 3g/liter", "Chlorothalonil 2g/liter"],
        "organic_medicine": ["Neem oil 5ml/liter water", "Trichoderma 5g/liter spray", "Baking soda solution 5g/liter"],
        "prevention": "Remove infected leaves, avoid overhead watering, ensure proper spacing",
        "பெயர்": "இலைப் புள்ளி",
        "வகை": "பூஞ்சை",
        "உரம்": "நுண்ணூட்டச்சத்துகளுடன் கூடிய சமநிலை NPK (80:40:40 kg/ஏக்கர்)",
        "நீர்": "65%",
        "மருந்து": ["மேன்கோசெப் 2.5g/லிட்டர் நீர்", "காப்பர் ஆக்சிக்ளோரைடு 3g/லிட்டர்", "குளோரோதலோனில் 2g/லிட்டர்"],
        "கரிம மருந்து": ["வேப்ப எண்ணெய் 5ml/லிட்டர் நீர்", "ட்ரைகோடெர்மா 5g/லிட்டர் தெளிப்பு", "பேக்கிங் சோடா கரைசல் 5g/லிட்டர்"],
        "தடுப்பு முறைகள்": "பாதிக்கப்பட்ட இலைகளை அகற்றுதல், மேல் நீர்ப்பாசனம் தவிர்த்தல், சரியான இடைவெளி உறுதி செய்தல்",
        "नाम": "पत्ती धब्बा",
        "प्रकार": "फफूंदी",
        "उर्वरक": "सूक्ष्म पोषक तत्वों के साथ संतुलित NPK (80:40:40 kg/एकड़)",
        "पानी": "65%",
        "दवा": ["मैन्कोज़ेब 2.5g/लीटर पानी", "कॉपर ऑक्सीक्लोराइड 3g/लीटर", "क्लोरोथैलोनिल 2g/लीटर"],
        "जैविक दवा": ["नीम का तेल 5ml/लीटर पानी", "ट्राइकोडर्मा 5g/लीटर स्प्रे", "बेकिंग सोडा घोल 5g/लीटर"],
        "रोकथाम": "संक्रमित पत्तियों को हटाएं, ऊपरी सिंचाई से बचें, उचित अंतर सुनिश्चित करें",
        "പേര്": "ഇല പുള്ളി",
        "തരം": "ഫംഗസ്",
        "വളം": "സൂക്ഷ്മ പോഷകങ്ങളുള്ള സന്തുലിത NPK (80:40:40 kg/ഏക്കർ)",
        "വെള്ളം": "65%",
        "മരുന്ന്": ["മാങ്കോസെബ് 2.5g/ലിറ്റർ വെള്ളം", "കോപ്പർ ഓക്സിക്ലോറൈഡ് 3g/ലിറ്റർ", "ക്ലോറോതലോനിൽ 2g/ലിറ്റർ വെള്ളം"],
        "ജൈവ മരുന്ന്": ["വേപ്പെണ്ണ 5ml/ലിറ്റർ വെള്ളം", "ട്രൈക്കോഡെർമ 5g/ലിറ്റർ സ്പ്രേ", "ബേക്കിംഗ് സോഡ ലായനി 5g/ലിറ്റർ"],
        "തടയൽ": "ബാധിച്ച ഇലകൾ നീക്കം ചെയ്യുക, മുകളിലൂടെയുള്ള ജലസേചനം ഒഴിവാക്കുക, ശരിയായ അകലം ഉറപ്പാക്കുക",
        "పేరు": "ఆకు చుక్క",
        "రకం": "ఫంగస్",
        "ఎరువు": "సూక్ష్మ పోషకాలతో సమతుల్య NPK (80:40:40 kg/ఎకరం)",
        "నీరు": "65%",
        "మందు": ["మ్యాంకోజెబ్ 2.5g/లీటరు నీరు", "కాపర్ ఆక్సిక్లోరైడ్ 3g/లీటరు", "క్లోరోతలోనిల్ 2g/లీటరు నీరు"],
        "సేంద్రియ మందు": ["వేప నూనె 5ml/లీటరు నీరు", "ట్రైకోడెర్మా 5g/లీటరు స్ప్రే", "బేకింగ్ సోడా ద్రావణం 5g/లీటరు"],
        "నివారణ": "బాధిత ఆకులను తీసివేయండి, పై నీటిపారుదల నివారించండి, సరైన అంతరాన్ని నిర్ధారించండి",
        "ಹೆಸರು": "ಎಲೆ ಕಲೆ",
        "ರೀತಿ": "ಶಿಲೀಂಧ್ರ",
        "ಎರುವು": "ಸೂಕ್ಷ್ಮ ಪೋಷಕಾಂಶಗಳೊಂದಿಗೆ ಸಮತೋಲಿತ NPK (80:40:40 kg/ಎಕರೆ)",
        "ನೀರು": "65%",
        "ಮದ್ದು": ["ಮ್ಯಾಂಕೋಜೆಬ್ 2.5g/ಲೀಟರ್ ನೀರು", "ಕಾಪರ್ ಆಕ್ಸಿಕ್ಲೋರೈಡ್ 3g/ಲೀಟರ್", "ಕ್ಲೋರೋತಲೋನಿಲ್ 2g/ಲೀಟರ್ ನೀರು"],
        "ಸಾವಯವ ಮದ್ದು": ["ಬೇವಿನ ಎಣ್ಣೆ 5ml/ಲೀಟರ್ ನೀರು", "ಟ್ರೈಕೋಡರ್ಮ 5g/ಲೀಟರ್ ಸಿಂಪಡಿಕೆ", "ಬೇಕಿಂಗ್ ಸೋಡಾ ದ್ರಾವಣ 5g/ಲೀಟರ್"],
        "ತಡೆಗಟ್ಟುವಿಕೆ": "ಬಾಧಿತ ಎಲೆಗಳನ್ನು ತೆಗೆದುಹಾಕಿ, ಮೇಲಿನ ನೀರಾವರಿ ತಪ್ಪಿಸಿ, ಸರಿಯಾದ ಅಂತರ ಖಾತರಿಪಡಿಸಿ",
        "نام": "پتی کا دھبہ",
        "قسم": "فنگس",
        "کھاد": "مائیکرو نیوٹرینٹس کے ساتھ متوازن NPK (80:40:40 kg/ایکڑ)",
        "پانی": "65%",
        "دوا": ["مینکوزیب 2.5g/لٹر پانی", "کاپر آکسی کلورائیڈ 3g/لٹر", "کلوروتھیلونیل 2g/لٹر پانی"],
        "نامیاتی دوا": ["نیم کا تیل 5ml/لٹر پانی", "ٹرائیکوڈرما 5g/لٹر سپرے", "بیکنگ سوڈا محلول 5g/لٹر"],
        "روک تھام": "متاثرہ پتیوں کو ہٹائیں، اوور ہیڈ آبپاشی سے بچیں، مناسب فاصلہ یقینی بنائیں"
    },

    "Longhorn Beetle (Dihammus cervinus)": {
        "type": "insect pest",
        "fertilizer": "Balanced NPK (80:40:40 kg/acre) with micronutrients",
        "water": "60%",
        "medicine": ["Chlorpyrifos 2.5ml/liter water", "Monocrotophos 1.5ml/liter", "Dichlorvos 1ml/liter"],
        "organic_medicine": ["Neem oil 10ml/liter water", "Karanj oil 5ml/liter", "Garlic extract 15ml/liter"],
        "prevention": "Remove and destroy infested wood, use pheromone traps, maintain tree health",
        "பெயர்": "நீண்ட கொம்பு வண்டு (டிஹாம்மஸ் செர்வினஸ்)",
        "வகை": "பூச்சி கொல்லி",
        "உரம்": "நுண்ணூட்டச்சத்துகளுடன் கூடிய சமநிலை NPK (80:40:40 kg/ஏக்கர்)",
        "நீர்": "60%",
        "மருந்து": ["குளோர்பைரிஃபாஸ் 2.5ml/லிட்டர் நீர்", "மோனோகிரோடோபோஸ் 1.5ml/லிட்டர்", "டைக்ளோர்வாஸ் 1ml/லிட்டர்"],
        "கரிம மருந்து": ["வேப்ப எண்ணெய் 10ml/லிட்டர் நீர்", "கரஞ்ச எண்ணெய் 5ml/லிட்டர்", "பூண்டு சாறு 15ml/லிட்டர் நீர்"],
        "தடுப்பு முறைகள்": "பாதிக்கப்பட்ட மரத்தை அகற்றி அழித்தல், ஃபெரோமோன் பொறிகளைப் பயன்படுத்துதல், மரத்தின் ஆரோக்கியத்தைப் பேணுதல்",
        "नाम": "लॉन्गहॉर्न बीटल (डिहैमस सेर्विनस)",
        "प्रकार": "कीट कीट",
        "उर्वरक": "सूक्ष्म पोषक तत्वों के साथ संतुलित NPK (80:40:40 kg/एकड़)",
        "पानी": "60%",
        "दवा": ["क्लोरपाइरीफॉस 2.5ml/लीटर पानी", "मोनोक्रोटोफोस 1.5ml/लीटर", "डाइक्लोरवोस 1ml/लीटर"],
        "जैविक दवा": ["नीम का तेल 10ml/लीटर पानी", "करंज का तेल 5ml/लीटर", "लहसुन का अर्क 15ml/लीटर पानी"],
        "रोकथाम": "संक्रमित लकड़ी को हटाएं और नष्ट करें, फेरोमोन जाल का उपयोग करें, पेड़ के स्वास्थ्य को बनाए रखें",
        "പേര്": "ലോംഗ്ഹോൺ ബീറ്റിൽ (ഡിഹാമസ് സെർവിനസ്)",
        "തരം": "പ്രാണികൾ",
        "വളം": "സൂക്ഷ്മ പോഷകങ്ങളുള്ള സന്തുലിത NPK (80:40:40 kg/ഏക്കർ)",
        "വെള്ളം": "60%",
        "മരുന്ന്": ["ക്ലോർപൈറിഫോസ് 2.5ml/ലിറ്റർ വെള്ളം", "മോണോക്രോട്ടോഫോസ് 1.5ml/ലിറ്റർ", "ഡൈക്ലോർവോസ് 1ml/ലിറ്റർ"],
        "ജൈവ മരുന്ന്": ["വേപ്പെണ്ണ 10ml/ലിറ്റർ വെള്ളം", "കരിഞ്ചണ്ണ 5ml/ലിറ്റർ", "വെളുത്തുള്ളി സത്ത് 15ml/ലിറ്റർ വെള്ളം"],
        "തടയൽ": "ബാധിച്ച മരം നീക്കംചെയ്ത് നശിപ്പിക്കുക, ഫെറോമോൺ കുടുക്കുകൾ ഉപയോഗിക്കുക, വൃക്ഷത്തിന്റെ ആരോഗ്യം നിലനിർത്തുക",
        "పేరు": "లాంగ్హార్న్ బీటిల్ (డిహామస్ సర్వినస్)",
        "రకం": "కీటకం",
        "ఎరువు": "సూక్ష్మ పోషకాలతో సమతుల్య NPK (80:40:40 kg/ఎకరం)",
        "నీరు": "60%",
        "మందు": ["క్లోర్పైరిఫాస్ 2.5ml/లీటరు నీరు", "మోనోక్రోటోఫాస్ 1.5ml/లీటరు", "డైక్లోర్వోస్ 1ml/లీటరు"],
        "సేంద్రియ మందు": ["వేప నూనె 10ml/లీటరు నీరు", "కరంజ నూనె 5ml/లీటరు", "వెల్లుల్లి సారం 15ml/లీటరు నీరు"],
        "నివారణ": "బాధిత చెక్కను తీసివేసి నాశనం చేయండి, ఫెరోమోన్ ట్రాప్లను ఉపయోగించండి, చెట్టు ఆరోగ్యాన్ని నిర్వహించండి",
        "ಹೆಸರು": "ಲಾಂಗ್ಹಾರ್ನ್ ಬೀಟಲ್ (ಡಿಹ್ಯಾಮಸ್ ಸರ್ವಿನಸ್)",
        "ರೀತಿ": "ಕೀಟ",
        "ಎರುವು": "ಸೂಕ್ಷ್ಮ ಪೋಷಕಾಂಶಗಳೊಂದಿಗೆ ಸಮತೋಲಿತ NPK (80:40:40 kg/ಎಕರೆ)",
        "ನೀರು": "60%",
        "ಮದ್ದು": ["ಕ್ಲೋರ್ಪೈರಿಫೋಸ್ 2.5ml/ಲೀಟರ್ ನೀರು", "ಮೊನೊಕ್ರೊಟೊಫೋಸ್ 1.5ml/ಲೀಟರ್", "ಡೈಕ್ಲೋರ್ವೋಸ್ 1ml/ಲೀಟರ್"],
        "ಸಾವಯವ ಮದ್ದು": ["ಬೇವಿನ ಎಣ್ಣೆ 10ml/ಲೀಟರ್ ನೀರು", "ಕರಂಜ ಎಣ್ಣೆ 5ml/ಲೀಟರ್", "ಬೆಳ್ಳುಳ್ಳಿ ಸಾರ 15ml/ಲೀಟರ್ ನೀರು"],
        "ತಡೆಗಟ್ಟುವಿಕೆ": "ಬಾಧಿತ ಮರವನ್ನು ತೆಗೆದುಹಾಕಿ ನಾಶಪಡಿಸಿ, ಫೆರೊಮೋನ್ ಬಲೆಗಳನ್ನು ಬಳಸಿ, ಮರದ ಆರೋಗ್ಯವನ್ನು ಕಾಪಾಡಿಕೊಳ್ಳಿ",
        "نام": "لانگ ہارن بیٹل (ڈیہیمس سروینس)",
        "قسم": "کیڑا",
        "کھاد": "مائیکرو نیوٹرینٹس کے ساتھ متوازن NPK (80:40:40 kg/ایکڑ)",
        "پانی": "60%",
        "دوا": ["کلورپائریفاس 2.5ml/لٹر پانی", "مونوکروٹوفوس 1.5ml/لٹر", "ڈائیکلورووس 1ml/لٹر"],
        "نامیاتی دوا": ["نیم کا تیل 10ml/لٹر پانی", "کرنج کا تیل 5ml/لٹر", "لہسن کا عرق 15ml/لٹر پانی"],
        "روک تھام": "متاثرہ لکڑی کو ہٹا کر تباہ کریں، فیرومون ٹریپس استعمال کریں، درخت کی صحت برقرار رکھیں"
    },

    "Powdery_Mildew": {
        "type": "fungal",
        "fertilizer": "Balanced NPK (80:40:40 kg/acre) with micronutrients",
        "water": "55%",
        "medicine": ["Sulfur 3g/liter water", "Dinocap 1ml/liter", "Myclobutanil 0.5g/liter"],
        "organic_medicine": ["Baking soda solution 5g/liter water", "Milk spray 1:10 dilution", "Neem oil 5ml/liter water"],
        "prevention": "Improve air circulation, avoid overhead watering, remove infected leaves",
        "பெயர்": "பவுடரி பூஞ்சை",
        "வகை": "பூஞ்சை",
        "உரம்": "நுண்ணூட்டச்சத்துகளுடன் கூடிய சமநிலை NPK (80:40:40 kg/ஏக்கர்)",
        "நீர்": "55%",
        "மருந்து": ["சல்பர் 3g/லிட்டர் நீர்", "டைனோகேப் 1ml/லிட்டர்", "மைக்ளோபுடனில் 0.5g/லிட்டர்"],
        "கரிம மருந்து": ["பேக்கிங் சோடா கரைசல் 5g/லிட்டர் நீர்", "பால் தெளிப்பு 1:10 நீர்த்தல்", "வேப்ப எண்ணெய் 5ml/லிட்டர் நீர்"],
        "தடுப்பு முறைகள்": "காற்று சுழற்சியை மேம்படுத்துதல், மேல் நீர்ப்பாசனம் தவிர்த்தல், பாதிக்கப்பட்ட இலைகளை அகற்றுதல்",
        "नाम": "पाउडरी मिल्ड्यू",
        "प्रकार": "फफूंदी",
        "उर्वरक": "सूक्ष्म पोषक तत्वों के साथ संतुलित NPK (80:40:40 kg/एकड़)",
        "पानी": "55%",
        "दवा": ["सल्फर 3g/लीटर पानी", "डिनोकैप 1ml/लीटर", "माइक्लोब्यूटानिल 0.5g/लीटर"],
        "जैविक दवा": ["बेकिंग सोडा घोल 5g/लीटर पानी", "दूध स्प्रे 1:10 कमजोर पड़ना", "नीम का तेल 5ml/लीटर पानी"],
        "रोकथाम": "वायु परिसंचरण में सुधार करें, ऊपरी सिंचाई से बचें, संक्रमित पत्तियों को हटाएं",
        "പേര്": "പൗഡറി മിൽഡ്യൂ",
        "തരം": "ഫംഗസ്",
        "വളം": "സൂക്ഷ്മ പോഷകങ്ങളുള്ള സന്തുലിത NPK (80:40:40 kg/ഏക്കർ)",
        "വെള്ളം": "55%",
        "മരുന്ന്": ["സൾഫർ 3g/ലിറ്റർ വെള്ളം", "ഡൈനോകാപ്പ് 1ml/ലിറ്റർ", "മൈക്ലോബ്യൂട്ടാനിൽ 0.5g/ലിറ്റർ"],
        "ജൈവ മരുന്ന്": ["ബേക്കിംഗ് സോഡ ലായനി 5g/ലിറ്റർ വെള്ളം", "പാൽ സ്പ്രേ 1:10 ഡൈലൂഷൻ", "വേപ്പെണ്ണ 5ml/ലിറ്റർ വെള്ളം"],
        "തടയൽ": "വായു പ്രചരണം മെച്ചപ്പെടുത്തുക, മുകളിലൂടെയുള്ള ജലസേചനം ഒഴിവാക്കുക, ബാധിച്ച ഇലകൾ നീക്കം ചെയ്യുക",
        "పేరు": "పౌడరీ మిల్డ్యూ",
        "రకం": "ఫంగస్",
        "ఎరువు": "సూక్ష్మ పోషకాలతో సమతుల్య NPK (80:40:40 kg/ఎకరం)",
        "నీరు": "55%",
        "మందు": ["సల్ఫర్ 3g/లీటరు నీరు", "డైనోక్యాప్ 1ml/లీటరు", "మైక్లోబ్యూటానిల్ 0.5g/లీటరు"],
        "సేంద్రియ మందు": ["బేకింగ్ సోడా ద్రావణం 5g/లీటరు నీరు", "పాలు స్ప్రే 1:10 డైల్యూషన్", "వేప నూనె 5ml/లీటరు నీరు"],
        "నివారణ": "గాలి ప్రసరణ మెరుగుపరచండి, పై నీటిపారుదల నివారించండి, బాధిత ఆకులను తీసివేయండి",
        "ಹೆಸರು": "ಪೌಡರಿ ಮಿಲ್ಡ್ಯೂ",
        "ರೀತಿ": "ಶಿಲೀಂಧ್ರ",
        "ಎರುವು": "ಸೂಕ್ಷ್ಮ ಪೋಷಕಾಂಶಗಳೊಂದಿಗೆ ಸಮತೋಲಿತ NPK (80:40:40 kg/ಎಕರೆ)",
        "ನೀರು": "55%",
        "ಮದ್ದು": ["ಸಲ್ಫರ್ 3g/ಲೀಟರ್ ನೀರು", "ಡೈನೊಕ್ಯಾಪ್ 1ml/ಲೀಟರ್", "ಮೈಕ್ಲೊಬ್ಯೂಟಾನಿಲ್ 0.5g/ಲೀಟರ್"],
        "ಸಾವಯವ ಮದ್ದು": ["ಬೇಕಿಂಗ್ ಸೋಡಾ ದ್ರಾವಣ 5g/ಲೀಟರ್ ನೀರು", "ಹಾಲು ಸಿಂಪಡಣೆ 1:10 ದುರ್ಬಲಗೊಳಿಸುವಿಕೆ", "ಬೇವಿನ ಎಣ್ಣೆ 5ml/ಲೀಟರ್ ನೀರು"],
        "ತಡೆಗಟ್ಟುವಿಕೆ": "ವಾಯು ಸಂಚಾರ ಸುಧಾರಿಸಿ, ಮೇಲಿನ ನೀರಾವರಿ ತಪ್ಪಿಸಿ, ಬಾಧಿತ ಎಲೆಗಳನ್ನು ತೆಗೆದುಹಾಕಿ",
        "نام": "پاؤڈری ملڈیو",
        "قسم": "فنگس",
        "کھاد": "مائیکرو نیوٹرینٹس کے ساتھ متوازن NPK (80:40:40 kg/ایکڑ)",
        "پانی": "55%",
        "دوا": ["سلفر 3g/لٹر پانی", "ڈائنوکیپ 1ml/لٹر", "مائیکلوبیوٹانل 0.5g/لٹر"],
        "نامیاتی دوا": ["بیکنگ سوڈا محلول 5g/لٹر پانی", "دودھ سپرے 1:10 dilution", "نیم کا تیل 5ml/لٹر پانی"],
        "روک تھام": "ہوا کی گردش بہتر بنائیں، اوور ہیڈ آبپاشی سے گریز کریں، متاثرہ پتیوں کو ہٹائیں"
    },

    "Root_Basal_Rot": {
        "type": "fungal",
        "fertilizer": "Balanced NPK (80:40:40 kg/acre) with micronutrients",
        "water": "50%",
        "medicine": ["Carbendazim 1g/liter water", "Thiophanate-methyl 1.5g/liter", "Metalaxyl 2g/liter"],
        "organic_medicine": ["Trichoderma 10g/liter water", "Pseudomonas fluorescens 10g/liter", "Neem cake 100kg/acre"],
        "prevention": "Improve drainage, avoid waterlogging, use disease-free planting material",
        "பெயர்": "வேர் அடி அழுகல்",
        "வகை": "பூஞ்சை",
        "உரம்": "நுண்ணூட்டச்சத்துகளுடன் கூடிய சமநிலை NPK (80:40:40 kg/ஏக்கர்)",
        "நீர்": "50%",
        "மருந்து": ["கார்பெண்டாசிம் 1g/லிட்டர் நீர்", "தையோபெனேட்-மெத்தில் 1.5g/லிட்டர்", "மெட்டலாக்ஸில் 2g/லிட்டர்"],
        "கரிம மருந்து": ["ட்ரைகோடெர்மா 10g/லிட்டர் நீர்", "சூடோமோனாஸ் புளோரசன்ஸ் 10g/லிட்டர்", "வேம்பு கேக் 100kg/ஏக்கர்"],
        "தடுப்பு முறைகள்": "வடிகால் மேம்படுத்துதல், நீர் தேங்குதலைத் தவிர்த்தல், நோயற்ற நடவுப் பொருட்களைப் பயன்படுத்துதல்",
        "नाम": "जड़ आधार सड़न",
        "प्रकार": "फफूंदी",
        "उर्वरक": "सूक्ष्म पोषक तत्वों के साथ संतुलित NPK (80:40:40 kg/एकड़)",
        "पानी": "50%",
        "दवा": ["कार्बेन्डाजिम 1g/लीटर पानी", "थायोफेनेट-मेथिल 1.5g/लीटर", "मेटालैक्सिल 2g/लीटर"],
        "जैविक दवा": ["ट्राइकोडर्मा 10g/लीटर पानी", "स्यूडोमोनास फ्लोरोसेंस 10g/लीटर", "नीम की खली 100kg/एकड़"],
        "रोकथाम": "जल निकासी में सुधार करें, जलभराव से बचें, रोगमुक्त रोपण सामग्री का उपयोग करें",
        "പേര്": "വേരടി ചീച്ചിൽ",
        "തരം": "ഫംഗസ്",
        "വളം": "സൂക്ഷ്മ പോഷകങ്ങളുള്ള സന്തുലിത NPK (80:40:40 kg/ഏക്കർ)",
        "വെള്ളം": "50%",
        "മരുന്ന്": ["കാർബൻഡാസിം 1g/ലിറ്റർ വെള്ളം", "തിയോഫനേറ്റ്-മെത്തിൽ 1.5g/ലിറ്റർ", "മെറ്റാലാക്സിൽ 2g/ലിറ്റർ"],
        "ജൈവ മരുന്ന്": ["ട്രൈക്കോഡെർമ 10g/ലിറ്റർ വെള്ളം", "സ്യൂഡോമോണാസ് ഫ്ലൂറസെൻസ് 10g/ലിറ്റർ", "വേപ്പുമാവ് 100kg/ഏക്കർ"],
        "തടയൽ": "ജലനിരപ്പ് മെച്ചപ്പെടുത്തുക, വെള്ളം തങ്ങൽ ഒഴിവാക്കുക, രോഗമുക്ത നടീൽ വസ്തുക്കൾ ഉപയോഗിക്കുക",
        "పేరు": "రూట్ బేసల్ రాట్",
        "రకం": "ఫంగస్",
        "ఎరువు": "సూక్ష్మ పోషకాలతో సమతుల్య NPK (80:40:40 kg/ఎకరం)",
        "నీరు": "50%",
        "మందు": ["కార్బెండాజిమ్ 1g/లీటరు నీరు", "థియోఫెనేట్-మిథైల్ 1.5g/లీటరు", "మెటాలాక్సిల్ 2g/లీటరు"],
        "సేంద్రియ మందు": ["ట్రైకోడెర్మా 10g/లీటరు నీరు", "సూడోమోనాస్ ఫ్లోరసెన్స్ 10g/లీటరు", "వేప చెక్క 100kg/ఎకరం"],
        "నివారణ": "నీటి వద్దులు మెరుగుపరచండి, నీటి నిల్వలను నివారించండి, వ్యాధి రహిత నాటు పదార్థాలను ఉపయోగించండి",
        "ಹೆಸರು": "ಬೇರು ಮೂಲ ಕೊಳೆತ",
        "ರೀತಿ": "ಶಿಲೀಂಧ್ರ",
        "ಎರುವು": "ಸೂಕ್ಷ್ಮ ಪೋಷಕಾಂಶಗಳೊಂದಿಗೆ ಸಮತೋಲಿತ NPK (80:40:40 kg/ಎಕರೆ)",
        "ನೀರು": "50%",
        "ಮದ್ದು": ["ಕಾರ್ಬೆಂಡಾಜಿಮ್ 1g/ಲೀಟರ್ ನೀರು", "ಥಯೋಫೆನೇಟ್-ಮೆಥೈಲ್ 1.5g/ಲೀಟರ್", "ಮೆಟಾಲಾಕ್ಸಿಲ್ 2g/ಲೀಟರ್"],
        "ಸಾವಯವ ಮದ್ದು": ["ಟ್ರೈಕೋಡರ್ಮ 10g/ಲೀಟರ್ ನೀರು", "ಸೂಡೋಮೊನಾಸ್ ಫ್ಲೂರಸೆನ್ಸ್ 10g/ಲೀಟರ್", "ಬೇವಿನ ಹಿಂಡಿ 100kg/ಎಕರೆ"],
        "ತಡೆಗಟ್ಟುವಿಕೆ": "ಜಲನಿಕ್ಷೇಪ ಸುಧಾರಿಸಿ, ನೀರು ತುಂಬಿಕೊಳ್ಳುವುದನ್ನು ತಪ್ಪಿಸಿ, ರೋಗರಹಿತ ನೆಡುವ ವಸ್ತು ಬಳಸಿ",
        "نام": "جڑ بنیادی سڑن",
        "قسم": "فنگس",
        "کھاد": "مائیکرو نیوٹرینٹس کے ساتھ متوازن NPK (80:40:40 kg/ایکڑ)",
        "پانی": "50%",
        "دوا": ["کاربینڈازیم 1g/لٹر پانی", "تھائیوفینیٹ میتھائل 1.5g/لٹر", "میٹالاکسل 2g/لٹر"],
        "نامیاتی دوا": ["ٹرائیکوڈرما 10g/لٹر پانی", "سوڈوموناس فلورسینس 10g/لٹر", "نیم کا کیک 100kg/ایکڑ"],
        "روک تھام": "نکاسی آب بہتر بنائیں، پانی بھرنے سے بچیں، بیماری سے پاک پودے لگانے والا مواد استعمال کریں"
    },

    "Teak defoliator": {
        "type": "insect pest",
        "fertilizer": "Balanced NPK (80:40:40 kg/acre) with micronutrients",
        "water": "65%",
        "medicine": ["Quinalphos 2ml/liter water", "Monocrotophos 1.5ml/liter", "Chlorpyrifos 2.5ml/liter"],
        "organic_medicine": ["Neem oil 10ml/liter water", "Karanj oil 5ml/liter", "Garlic extract 15ml/liter"],
        "prevention": "Collect and destroy larvae, maintain tree health, use light traps",
        "பெயர்": "தேக்கு இலை உண்ணி",
        "வகை": "பூச்சி கொல்லி",
        "உரம்": "நுண்ணூட்டச்சத்துகளுடன் கூடிய சமநிலை NPK (80:40:40 kg/ஏக்கர்)",
        "நீர்": "65%",
        "மருந்து": ["குவினால்பாஸ் 2ml/லிட்டர் நீர்", "மோனோகிரோடோபோஸ் 1.5ml/லிட்டர்", "குளோர்பைரிஃபாஸ் 2.5ml/லிட்டர்"],
        "கரிம மருந்து": ["வேப்ப எண்ணெய் 10ml/லிட்டர் நீர்", "கரஞ்ச எண்ணெய் 5ml/லிட்டர்", "பூண்டு சாறு 15ml/லிட்டர் நீர்"],
        "தடுப்பு முறைகள்": "லார்வாக்களை சேகரித்து அழித்தல், மரத்தின் ஆரோக்கியத்தைப் பேணுதல், ஒளிப் பொறிகளைப் பயன்படுத்துதல்",
        "नाम": "टीक डिफोलिएटर",
        "प्रकार": "कीट कीट",
        "उर्वरक": "सूक्ष्म पोषक तत्वों के साथ संतुलित NPK (80:40:40 kg/एकड़)",
        "पानी": "65%",
        "दवा": ["क्विनाल्फोस 2ml/लीटर पानी", "मोनोक्रोटोफोस 1.5ml/लीटर", "क्लोरपाइरीफॉस 2.5ml/लीटर"],
        "जैविक दवा": ["नीम का तेल 10ml/लीटर पानी", "करंज का तेल 5ml/लीटर", "लहसुन का अर्क 15ml/लीटर पानी"],
        "रोकथाम": "लार्वा इकट्ठा करें और नष्ट करें, पेड़ के स्वास्थ्य को बनाए रखें, प्रकाश जाल का उपयोग करें",
        "പേര്": "തേക്ക് ഇല തിന്നുന്ന കീടം",
        "തരം": "പ്രാണികൾ",
        "വളം": "സൂക്ഷ്മ പോഷകങ്ങളുള്ള സന്തുലിത NPK (80:40:40 kg/ഏക്കർ)",
        "വെള്ളം": "65%",
        "മരുന്ന്": ["ക്വിനാൽഫോസ് 2ml/ലിറ്റർ വെള്ളം", "മോണോക്രോട്ടോഫോസ് 1.5ml/ലിറ്റർ", "ക്ലോർപൈറിഫോസ് 2.5ml/ലിറ്റർ"],
        "ജൈവ മരുന്ന്": ["വേപ്പെണ്ണ 10ml/ലിറ്റർ വെള്ളം", "കരിഞ്ചണ്ണ 5ml/ലിറ്റർ", "വെളുത്തുള്ളി സത്ത് 15ml/ലിറ്റർ വെള്ളം"],
        "തടയൽ": "ലാർവകൾ ശേഖരിച്ച് നശിപ്പിക്കുക, വൃക്ഷത്തിന്റെ ആരോഗ്യം നിലനിർത്തുക, പ്രകാശ കുടുക്കുകൾ ഉപയോഗിക്കുക",
        "పేరు": "టీకు ఆకు తినే కీటకం",
        "రకం": "కీటకం",
        "ఎరువు": "సూక్ష్మ పోషకాలతో సమతుల్య NPK (80:40:40 kg/ఎకరం)",
        "నీరు": "65%",
        "మందు": ["క్వినాల్ఫాస్ 2ml/లీటరు నీరు", "మోనోక్రోటోఫాస్ 1.5ml/లీటరు", "క్లోర్పైరిఫాస్ 2.5ml/లీటరు"],
        "సేంద్రియ మందు": ["వేప నూనె 10ml/లీటరు నీరు", "కరంజ నూనె 5ml/లీటరు", "వెల్లుల్లి సారం 15ml/లీటరు నీరు"],
        "నివారణ": "లార్వాలను సేకరించి నాశనం చేయండి, చెట్టు ఆరోగ్యాన్ని నిర్వహించండి, లైట్ ట్రాప్లను ఉపయోగించండి",
        "ಹೆಸರು": "ಟೀಕು ಎಲೆ ತಿನ್ನುವ ಕೀಟ",
        "ರೀತಿ": "ಕೀಟ",
        "ಎರುವು": "ಸೂಕ್ಷ್ಮ ಪೋಷಕಾಂಶಗಳೊಂದಿಗೆ ಸಮತೋಲಿತ NPK (80:40:40 kg/ಎಕರೆ)",
        "ನೀರು": "65%",
        "ಮದ್ದು": ["ಕ್ವಿನಾಲ್ಫೋಸ್ 2ml/ಲೀಟರ್ ನೀರು", "ಮೊನೊಕ್ರೊಟೊಫೋಸ್ 1.5ml/ಲೀಟರ್", "ಕ್ಲೋರ್ಪೈರಿಫೋಸ್ 2.5ml/ಲೀಟರ್"],
        "ಸಾವಯವ ಮದ್ದು": ["ಬೇವಿನ ಎಣ್ಣೆ 10ml/ಲೀಟರ್ ನೀರು", "ಕರಂಜ ಎಣ್ಣೆ 5ml/ಲೀಟರ್", "ಬೆಳ್ಳುಳ್ಳಿ ಸಾರ 15ml/ಲೀಟರ್ ನೀರು"],
        "ತಡೆಗಟ್ಟುವಿಕೆ": "ಲಾರ್ವಾಗಳನ್ನು ಸಂಗ್ರಹಿಸಿ ನಾಶಮಾಡಿ, ಮರದ ಆರೋಗ್ಯವನ್ನು ಕಾಪಾಡಿಕೊಳ್ಳಿ, ಬೆಳಕಿನ ಬಲೆಗಳನ್ನು ಬಳಸಿ",
        "نام": "تیک ڈیفولی ایٹر",
        "قسم": "کیڑا",
        "کھاد": "مائیکرو نیوٹرینٹس کے ساتھ متوازن NPK (80:40:40 kg/ایکڑ)",
        "پانی": "65%",
        "دوا": ["کوینالفاس 2ml/لٹر پانی", "مونوکروٹوفوس 1.5ml/لٹر", "کلورپائریفاس 2.5ml/لٹر"],
        "نامیاتی دوا": ["نیم کا تیل 10ml/لٹر پانی", "کرنج کا تیل 5ml/لٹر", "لہسن کا عرق 15ml/لٹر پانی"],
        "روک تھام": "لاروا جمع کریں اور تباہ کریں، درخت کی صحت برقرار رکھیں، لائٹ ٹریپس استعمال کریں"
    },

    "Teak Skeletonizer": {
        "type": "insect pest",
        "fertilizer": "Balanced NPK (80:40:40 kg/acre) with micronutrients",
        "water": "65%",
        "medicine": ["Quinalphos 2ml/liter water", "Monocrotophos 1.5ml/liter", "Chlorpyrifos 2.5ml/liter"],
        "organic_medicine": ["Neem oil 10ml/liter water", "Karanj oil 5ml/liter", "Garlic extract 15ml/liter"],
        "prevention": "Remove and destroy infested leaves, maintain tree health, use pheromone traps",
        "பெயர்": "தேக்கு எலும்புக்கூடு உருவாக்கி",
        "வகை": "பூச்சி கொல்லி",
        "உரம்": "நுண்ணூட்டச்சத்துகளுடன் கூடிய சமநிலை NPK (80:40:40 kg/ஏக்கர்)",
        "நீர்": "65%",
        "மருந்து": ["குவினால்பாஸ் 2ml/லிட்டர் நீர்", "மோனோகிரோடோபோஸ் 1.5ml/லிட்டர்", "குளோர்பைரிஃபாஸ் 2.5ml/லிட்டர்"],
        "கரிம மருந்து": ["வேப்ப எண்ணெய் 10ml/லிட்டர் நீர்", "கரஞ்ச எண்ணெய் 5ml/லிட்டர்", "பூண்டு சாறு 15ml/லிட்டர் நீர்"],
        "தடுப்பு முறைகள்": "பாதிக்கப்பட்ட இலைகளை அகற்றி அழித்தல், மரத்தின் ஆரோக்கியத்தைப் பேணுதல், ஃபெரோமோன் பொறிகளைப் பயன்படுத்துதல்",
        "नाम": "टीक स्केलेटनाइज़र",
        "प्रकार": "कीट कीट",
        "उर्वरक": "सूक्ष्म पोषक तत्वों के साथ संतुलित NPK (80:40:40 kg/एकड़)",
        "पानी": "65%",
        "दवा": ["क्विनाल्फोस 2ml/लीटर पानी", "मोनोक्रोटोफोस 1.5ml/लीटर", "क्लोरपाइरीफॉस 2.5ml/लीटर"],
        "जैविक दवा": ["नीम का तेल 10ml/लीटर पानी", "करंज का तेल 5ml/लीटर", "लहसुन का अर्क 15ml/लीटर पानी"],
        "रोकथाम": "संक्रमित पत्तियों को हटाएं और नष्ट करें, पेड़ के स्वास्थ्य को बनाए रखें, फेरोमोन जाल का उपयोग करें",
        "പേര്": "തേക്ക് അസ്ഥികൂടം ഉണ്ടാക്കുന്ന കീടം",
        "തരം": "പ്രാണികൾ",
        "വളം": "സൂക്ഷ്മ പോഷകങ്ങളുള്ള സന്തുലിത NPK (80:40:40 kg/ഏക്കർ)",
        "വെള്ളം": "65%",
        "മരുന്ന്": ["ക്വിനാൽഫോസ് 2ml/ലിറ്റർ വെള്ളം", "മോണോക്രോട്ടോഫോസ് 1.5ml/ലിറ്റർ", "ക്ലോർപൈറിഫോസ് 2.5ml/ലിറ്റർ"],
        "ജൈവ മരുന്ന്": ["വേപ്പെണ്ണ 10ml/ലിറ്റർ വെള്ളം", "കരിഞ്ചണ്ണ 5ml/ലിറ്റർ", "വെളുത്തുള്ളി സത്ത് 15ml/ലിറ്റർ വെള്ളം"],
        "തടയൽ": "ബാധിച്ച ഇലകൾ നീക്കംചെയ്ത് നശിപ്പിക്കുക, വൃക്ഷത്തിന്റെ ആരോഗ്യം നിലനിർത്തുക, ഫെറോമോൺ കുടുക്കുകൾ ഉപയോഗിക്കുക",
        "పేరు": "టీకు స్కెలిటనైజర్",
        "రకం": "కీటకం",
        "ఎరువు": "సూక్ష్మ పోషకాలతో సమతుల్య NPK (80:40:40 kg/ఎకరం)",
        "నీరు": "65%",
        "మందు": ["క్వినాల్ఫాస్ 2ml/లీటరు నీరు", "మోనోక్రోటోఫాస్ 1.5ml/లీటరు", "క్లోర్పైరిఫాస్ 2.5ml/లీటరు"],
        "సేంద్రియ మందు": ["వేప నూనె 10ml/లీటరు నీరు", "కరంజ నూనె 5ml/లీటరు", "వెల్లుల్లి సారం 15ml/లీటరు నీరు"],
        "నివారణ": "బాధిత ఆకులను తీసివేసి నాశనం చేయండి, చెట్టు ఆరోగ్యాన్ని నిర్వహించండి, ఫెరోమోన్ ట్రాప్లను ఉపయోగించండి",
        "ಹೆಸರು": "ಟೀಕು ಅಸ್ಥಿಪಂಜರ ಮಾಡುವ ಕೀಟ",
        "ರೀತಿ": "ಕೀಟ",
        "ಎರುವು": "ಸೂಕ್ಷ್ಮ ಪೋಷಕಾಂಶಗಳೊಂದಿಗೆ ಸಮತೋಲಿತ NPK (80:40:40 kg/ಎಕರೆ)",
        "ನೀರು": "65%",
        "ಮದ್ದು": ["ಕ್ವಿನಾಲ್ಫೋಸ್ 2ml/ಲೀಟರ್ ನೀರು", "ಮೊನೊಕ್ರೊಟೊಫೋಸ್ 1.5ml/ಲೀಟರ್", "ಕ್ಲೋರ್ಪೈರಿಫೋಸ್ 2.5ml/ಲೀಟರ್"],
        "ಸಾವಯವ ಮದ್ದು": ["ಬೇವಿನ ಎಣ್ಣೆ 10ml/ಲೀಟರ್ ನೀರು", "ಕರಂಜ ಎಣ್ಣೆ 5ml/ಲೀಟರ್", "ಬೆಳ್ಳುಳ್ಳಿ ಸಾರ 15ml/ಲೀಟರ್ ನೀರು"],
        "ತಡೆಗಟ್ಟುವಿಕೆ": "ಬಾಧಿತ ಎಲೆಗಳನ್ನು ತೆಗೆದುಹಾಕಿ ನಾಶಮಾಡಿ, ಮರದ ಆರೋಗ್ಯವನ್ನು ಕಾಪಾಡಿಕೊಳ್ಳಿ, ಫೆರೊಮೋನ್ ಬಲೆಗಳನ್ನು ಬಳಸಿ",
        "نام": "تیک اسکیلیٹنائزر",
        "قسم": "کیڑا",
        "کھاد": "مائیکرو نیوٹرینٹس کے ساتھ متوازن NPK (80:40:40 kg/ایکڑ)",
        "پانی": "65%",
        "دوا": ["کوینالفاس 2ml/لٹر پانی", "مونوکروٹوفوس 1.5ml/لٹر", "کلورپائریفاس 2.5ml/لٹر"],
        "نامیاتی دوا": ["نیم کا تیل 10ml/لٹر پانی", "کرنج کا تیل 5ml/لٹر", "لہسن کا عرق 15ml/لٹر پانی"],
        "روک تھام": "متاثرہ پتیوں کو ہٹا کر تباہ کریں، درخت کی صحت برقرار رکھیں، فیرومون ٹریپس استعمال کریں"
    },

    "Teak Stem Borer (Alcterogystia cadambae)": {
        "type": "insect pest",
        "fertilizer": "Balanced NPK (80:40:40 kg/acre) with micronutrients",
        "water": "60%",
        "medicine": ["Chlorpyrifos 2.5ml/liter water", "Monocrotophos 1.5ml/liter", "Dichlorvos 1ml/liter"],
        "organic_medicine": ["Neem oil 10ml/liter water", "Karanj oil 5ml/liter", "Garlic extract 15ml/liter"],
        "prevention": "Remove and destroy infested stems, maintain tree health, use pheromone traps",
        "பெயர்": "தேக்கு தண்டு துளைப்பான் (அல்டெரோஜிஸ்டியா கடம்பே)",
        "வகை": "பூச்சி கொல்லி",
        "உரம்": "நுண்ணூட்டச்சத்துகளுடன் கூடிய சமநிலை NPK (80:40:40 kg/ஏக்கர்)",
        "நீர்": "60%",
        "மருந்து": ["குளோர்பைரிஃபாஸ் 2.5ml/லிட்டர் நீர்", "மோனோகிரோடோபோஸ் 1.5ml/லிட்டர்", "டைக்ளோர்வாஸ் 1ml/லிட்டர்"],
        "கரிம மருந்து": ["வேப்ப எண்ணெய் 10ml/லிட்டர் நீர்", "கரஞ்ச எண்ணெய் 5ml/லிட்டர்", "பூண்டு சாறு 15ml/லிட்டர் நீர்"],
        "தடுப்பு முறைகள்": "பாதிக்கப்பட்ட தண்டுகளை அகற்றி அழித்தல், மரத்தின் ஆரோக்கியத்தைப் பேணுதல், ஃபெரோமோன் பொறிகளைப் பயன்படுத்துதல்",
        "नाम": "टीक स्टेम बोरर (एल्क्टेरोगिस्टिया कडम्बे)",
        "प्रकार": "कीट कीट",
        "उर्वरक": "सूक्ष्म पोषक तत्वों के साथ संतुलित NPK (80:40:40 kg/एकड़)",
        "पानी": "60%",
        "दवा": ["क्लोरपाइरीफॉस 2.5ml/लीटर पानी", "मोनोक्रोटोफोस 1.5ml/लीटर", "डाइक्लोरवोस 1ml/लीटर"],
        "जैविक दवा": ["नीम का तेल 10ml/लीटर पानी", "करंज का तेल 5ml/लीटर", "लहसुन का अर्क 15ml/लीटर पानी"],
        "रोकथाम": "संक्रमित तनों को हटाएं और नष्ट करें, पेड़ के स्वास्थ्य को बनाए रखें, फेरोमोन जाल का उपयोग करें",
        "പേര്": "തേക്ക് തണ്ട് തുളയ്ക്കുന്ന കീടം (ആൽട്ടെറോജിസ്റ്റിയ കടമ്പെ)",
        "തരം": "പ്രാണികൾ",
        "വളം": "സൂക്ഷ്മ പോഷകങ്ങളുള്ള സന്തുലിത NPK (80:40:40 kg/ഏക്കർ)",
        "വെള്ളം": "60%",
        "മരുന്ന്": ["ക്ലോർപൈറിഫോസ് 2.5ml/ലിറ്റർ വെള്ളം", "മോണോക്രോട്ടോഫോസ് 1.5ml/ലിറ്റർ", "ഡൈക്ലോർവോസ് 1ml/ലിറ്റർ"],
        "ജൈവ മരുന്ന്": ["വേപ്പെണ്ണ 10ml/ലിറ്റർ വെള്ളം", "കരിഞ്ചണ്ണ 5ml/ലിറ്റർ", "വെളുത്തുള്ളി സത്ത് 15ml/ലിറ്റർ വെള്ളം"],
        "തടയൽ": "ബാധിച്ച തണ്ടുകൾ നീക്കംചെയ്ത് നശിപ്പിക്കുക, വൃക്ഷത്തിന്റെ ആരോഗ്യം നിലനിർത്തുക, ഫെറോമോൺ കുടുക്കുകൾ ഉപയോഗിക്കുക",
        "పేరు": "టీకు స్టెమ్ బోరర్ (ఆల్టెరోజిస్టియా కడంబే)",
        "రకం": "కీటకం",
        "ఎరువు": "సూక్ష్మ పోషకాలతో సమతుల్య NPK (80:40:40 kg/ఎకరం)",
        "నీరు": "60%",
        "మందు": ["క్లోర్పైరిఫాస్ 2.5ml/లీటరు నీరు", "మోనోక్రోటోఫాస్ 1.5ml/లీటరు", "డైక్లోర్వోస్ 1ml/లీటరు"],
        "సేంద్రియ మందు": ["వేప నూనె 10ml/లీటరు నీరు", "కరంజ నూనె 5ml/లీటరు", "వెల్లుల్లి సారం 15ml/లీటరు నీరు"],
        "నివారణ": "బాధిత కాండాలను తీసివేసి నాశనం చేయండి, చెట్టు ఆరోగ్యాన్ని నిర్వహించండి, ఫెరోమోన్ ట్రాప్లను ఉపయోగించండి",
        "ಹೆಸರು": "ಟೀಕು ಕಾಂಡ ಕೊರೆಯುವ ಕೀಟ (ಆಲ್ಟೆರೋಜಿಸ್ಟಿಯ ಕಡಂಬೇ)",
        "ರೀತಿ": "ಕೀಟ",
        "ಎರುವು": "ಸೂಕ್ಷ್ಮ ಪೋಷಕಾಂಶಗಳೊಂದಿಗೆ ಸಮತೋಲಿತ NPK (80:40:40 kg/ಎಕರೆ)",
        "ನೀರು": "60%",
        "ಮದ್ದು": ["ಕ್ಲೋರ್ಪೈರಿಫೋಸ್ 2.5ml/ಲೀಟರ್ ನೀರು", "ಮೊನೊಕ್ರೊಟೊಫೋಸ್ 1.5ml/ಲೀಟರ್", "ಡೈಕ್ಲೋರ್ವೋಸ್ 1ml/ಲೀಟರ್"],
        "ಸಾವಯವ ಮದ್ದು": ["ಬೇವಿನ ಎಣ್ಣೆ 10ml/ಲೀಟರ್ ನೀರು", "ಕರಂಜ ಎಣ್ಣೆ 5ml/ಲೀಟರ್", "ಬೆಳ್ಳುಳ್ಳಿ ಸಾರ 15ml/ಲೀಟರ್ ನೀರು"],
        "ತಡೆಗಟ್ಟುವಿಕೆ": "ಬಾಧಿತ ಕಾಂಡಗಳನ್ನು ತೆಗೆದುಹಾಕಿ ನಾಶಮಾಡಿ, ಮರದ ಆರೋಗ್ಯವನ್ನು ಕಾಪಾಡಿಕೊಳ್ಳಿ, ಫೆರೊಮೋನ್ ಬಲೆಗಳನ್ನು ಬಳಸಿ",
        "نام": "تیک سٹیم بورر (الکتروجسٹیا کڈمبے)",
        "قسم": "کیڑا",
        "کھاد": "مائیکرو نیوٹرینٹس کے ساتھ متوازن NPK (80:40:40 kg/ایکڑ)",
        "پانی": "60%",
        "دوا": ["کلورپائریفاس 2.5ml/لٹر پانی", "مونوکروٹوفوس 1.5ml/لٹر", "ڈائیکلورووس 1ml/لٹر"],
        "نامیاتی دوا": ["نیم کا تیل 10ml/لٹر پانی", "کرنج کا تیل 5ml/لٹر", "لہسن کا عرق 15ml/لٹر پانی"],
        "روک تھام": "متاثرہ تنوں کو ہٹا کر تباہ کریں، درخت کی صحت برقرار رکھیں، فیرومون ٹریپس استعمال کریں"
    },

    "White Grubs and Termites (Holotrichia spp)": {
        "type": "insect pest",
        "fertilizer": "Balanced NPK (80:40:40 kg/acre) with micronutrients",
        "water": "55%",
        "medicine": ["Chlorpyrifos 2.5ml/liter water", "Phorate 2.5g/liter soil", "Carbofuran 2g/liter soil"],
        "organic_medicine": ["Neem cake 200kg/acre", "Karanj cake 150kg/acre", "Trichoderma 10g/liter water"],
        "prevention": "Deep plowing, remove crop residues, maintain soil health",
        "பெயர்": "வெள்ளைக் கம்பளிப்பூச்சிகள் மற்றும் கறையான்கள் (ஹோலோட்ரைக்கியா இனங்கள்)",
        "வகை": "பூச்சி கொல்லி",
        "உரம்": "நுண்ணூட்டச்சத்துகளுடன் கூடிய சமநிலை NPK (80:40:40 kg/ஏக்கர்)",
        "நீர்": "55%",
        "மருந்து": ["குளோர்பைரிஃபாஸ் 2.5ml/லிட்டர் நீர்", "ஃபோரேட் 2.5g/லிட்டர் மண்", "கார்போஃபியூரான் 2g/லிட்டர் மண்"],
        "கரிம மருந்து": ["வேம்பு கேக் 200kg/ஏக்கர்", "கரஞ்ச கேக் 150kg/ஏக்கர்", "ட்ரைகோடெர்மா 10g/லிட்டர் நீர்"],
        "தடுப்பு முறைகள்": "ஆழ உழுதல், பயிர் எச்சங்களை அகற்றுதல், மண்ணின் ஆரோக்கியத்தை பேணுதல்",
        "नाम": "सफेद ग्रब और दीमक (होलोट्राइकिया एसपीपी)",
        "प्रकार": "कीट कीट",
        "उर्वरक": "सूक्ष्म पोषक तत्वों के साथ संतुलित NPK (80:40:40 kg/एकड़)",
        "पानी": "55%",
        "दवा": ["क्लोरपाइरीफॉस 2.5ml/लीटर पानी", "फोरेट 2.5g/लीटर मिट्टी", "कार्बोफ्यूरन 2g/लीटर मिट्टी"],
        "जैविक दवा": ["नीम की खली 200kg/एकड़", "करंज की खली 150kg/एकड़", "ट्राइकोडर्मा 10g/लीटर पानी"],
        "रोकथाम": "गहरी जुताई, फसल अवशेषों को हटाएं, मिट्टी के स्वास्थ्य को बनाए रखें",
        "പേര്": "വെളുത്ത പുഴുക്കളും പുഴുക്കളും (ഹോലോട്രൈക്കിയ സ്പീഷീസ്)",
        "തരം": "പ്രാണികൾ",
        "വളം": "സൂക്ഷ്മ പോഷകങ്ങളുള്ള സന്തുലിത NPK (80:40:40 kg/ഏക്കർ)",
        "വെള്ളം": "55%",
        "മരുന്ന്": ["ക്ലോർപൈറിഫോസ് 2.5ml/ലിറ്റർ വെള്ളം", "ഫോറേറ്റ് 2.5g/ലിറ്റർ മണ്ണ്", "കാർബോഫ്യൂറൻ 2g/ലിറ്റർ മണ്ണ്"],
        "ജൈവ മരുന്ന്": ["വേപ്പുമാവ് 200kg/ഏക്കർ", "കരിഞ്ചമാവ് 150kg/ഏക്കർ", "ട്രൈക്കോഡെർമ 10g/ലിറ്റർ വെള്ളം"],
        "തടയൽ": "ആഴത്തിലുള്ള ഉഴവ്, കൃഷി അവശിഷ്ടങ്ങൾ നീക്കം ചെയ്യുക, മണ്ണിന്റെ ആരോഗ്യം നിലനിർത്തുക",
        "పేరు": "వైట్ గ్రబ్స్ మరియు తెనెలు (హోలోట్రిచియా జాతులు)",
        "రకం": "కీటకం",
        "ఎరువు": "సూక్ష్మ పోషకాలతో సమతుల్య NPK (80:40:40 kg/ఎకరం)",
        "నీరు": "55%",
        "మందు": ["క్లోర్పైరిఫాస్ 2.5ml/లీటరు నీరు", "ఫోరేట్ 2.5g/లీటరు నేల", "కార్బోఫ్యూరాన్ 2g/లీటరు నేల"],
        "సేంద్రియ మందు": ["వేప చెక్క 200kg/ఎకరం", "కరంజ చెక్క 150kg/ఎకరం", "ట్రైకోడెర్మా 10g/లీటరు నీరు"],
        "నివారణ": "లోతైన దున్నుట, పంట శేషాలను తొలగించండి, నేల ఆరోగ్యాన్ని నిర్వహించండి",
        "ಹೆಸರು": "ಬಿಳಿ ಗ್ರಬ್ಗಳು ಮತ್ತು ಪುರಿಯಲುಗಳು (ಹೊಲೊಟ್ರಿಕಿಯಾ ಪ್ರಭೇದಗಳು)",
        "ರೀತಿ": "ಕೀಟ",
        "ಎರುವು": "ಸೂಕ್ಷ್ಮ ಪೋಷಕಾಂಶಗಳೊಂದಿಗೆ ಸಮತೋಲಿತ NPK (80:40:40 kg/ಎಕರೆ)",
        "ನೀರು": "55%",
        "ಮದ್ದು": ["ಕ್ಲೋರ್ಪೈರಿಫೋಸ್ 2.5ml/ಲೀಟರ್ ನೀರು", "ಫೋರೇಟ್ 2.5g/ಲೀಟರ್ ಮಣ್ಣು", "ಕಾರ್ಬೊಫ್ಯೂರಾನ್ 2g/ಲೀಟರ್ ಮಣ್ಣು"],
        "ಸಾವಯವ ಮದ್ದು": ["ಬೇವಿನ ಹಿಂಡಿ 200kg/ಎಕರೆ", "ಕರಂಜ ಹಿಂಡಿ 150kg/ಎಕರೆ", "ಟ್ರೈಕೋಡರ್ಮ 10g/ಲೀಟರ್ ನೀರು"],
        "ತಡೆಗಟ್ಟುವಿಕೆ": "ಆಳವಾದ ಉಳುಮೆ, ಬೆಳೆ ಉಳಿಕೆಗಳನ್ನು ತೆಗೆದುಹಾಕಿ, ಮಣ್ಣಿನ ಆರೋಗ್ಯವನ್ನು ಕಾಪಾಡಿಕೊಳ್ಳಿ",
        "نام": "سفید گراب اور دیمک (ہولوٹرائیکیا انواع)",
        "قسم": "کیڑا",
        "کھاد": "مائیکرو نیوٹرینٹس کے ساتھ متوازن NPK (80:40:40 kg/ایکڑ)",
        "پانی": "55%",
        "دوا": ["کلورپائریفاس 2.5ml/لٹر پانی", "فوریٹ 2.5g/لٹر مٹی", "کاربوفیوران 2g/لٹر مٹی"],
        "نامیاتی دوا": ["نیم کا کیک 200kg/ایکڑ", "کرنج کا کیک 150kg/ایکڑ", "ٹرائیکوڈرما 10g/لٹر پانی"],
        "روک تھام": "گہری جوتائی، فصل کے باقیات ہٹائیں، مٹی کی صحت برقرار رکھیں"
    }
}